Workbook

Sheet Portada
B2: BASE DE DATOS TÉCNICA — SISTEMA CCTV INTEGRAL
B3: Plantilla editable · 20 marcas · 14 tipos de cámara · 5 variantes por tipo · 10 categorías de equipamiento · Precios en USD
B5: 20 | C5: 14 | D5: =COUNTA('Base de Datos'!$G$5:$G$972) -> 968 | E5: =COUNTIFS('Base de Datos'!$G$5:$G$972,"<>*No disponible*") -> 860 | F5: 10 | G5: =COUNTA(Equipamiento!$F$5:$F$66) -> 62
B6: Marcas | C6: Tipos de cámara | D6: Modelos de cámara | E6: Cámaras activas | F6: Categorías de equipo | G6: Equipos registrados
B9: Hoja | C9: Contenido
B10: =HYPERLINK("#'Resumen'!B2","Resumen") -> Resumen | C10: Cobertura marca × tipo, estadísticas de cámaras y equipamiento
B11: =HYPERLINK("#'Base de Datos'!B2","Base de Datos") -> Base de Datos | C11: Hoja maestra: 968 registros (5 variantes por tipo y marca) filtrables
B12: =HYPERLINK("#'Equipamiento'!B2","Equipamiento") -> Equipamiento | C12: NVR/DVR, HDD, switch PoE, UPS, monitores, rack, cableado, accesorios, fuentes y VMS
B13: =HYPERLINK("#'Comparativa'!B2","Comparativa") -> Comparativa | C13: Ficha comparativa por tipo (modelo premium / medio / económico)
B14: =HYPERLINK("#'Lista de Precios'!B2","Lista de Precios") -> Lista de Precios | C14: Cotización integral: sección A cámaras + sección B equipamiento
B15: Niveles de marca incluidos
B16: Nivel | C16: Marcas | D16: Enfoque
B17: Premium | C17: Axis, Bosch, Hanwha Vision, Avigilon, Pelco, Honeywell, MOBOTIX | D17: Máxima calidad óptica, analíticas y soporte; precio alto
B18: Premium (Cloud) / Medio-Alto | C18: Verkada · Vivotek, IDIS | D18: Gestión en la nube o gama profesional intermedia
B19: Medio | C19: Hikvision, Dahua, Uniview, Ubiquiti (UniFi Protect) | D19: La mejor relación precio/rendimiento del mercado
B20: Económico | C20: HiLook, Imou, EZVIZ, Reolink, TP-Link VIGI, Tenda | D20: Proyectos de bajo presupuesto; matrículas de las matrices Hikvision/Dahua
B23: Notas de uso
B24: 1. Las especificaciones y precios son referenciales (USD, mercado 2026); verifique siempre la ficha técnica vigente del fabricante antes de cotizar o instalar.
B25: 2. Filas «No disponible en portafolio» (marcadas en ámbar): la marca no fabrica ese tipo de cámara; en Observaciones se sugiere el equivalente de su matriz u otra marca.
B26: 3. Use los filtros de la fila de encabezados en Base de Datos (panel congelado en H5) y en Equipamiento (panel congelado en G5) para segmentar por marca, categoría, nivel o precio.
B27: 4. Hoja Equipamiento: NVR/DVR, discos de vigilancia, switch PoE, UPS, monitores, rack, cableado, accesorios, fuentes/PoE y software VMS (62 modelos de referencia).
B28: 5. En Lista de Precios, complete Cantidad y Descuento en ambas secciones (A cámaras / B equipamiento); los subtotales y el TOTAL GENERAL se calculan automáticamente.
B29: 6. Las columnas Proveedor y Stock están listas para registrar sus distribuidores locales (con listas desplegables en Categoría, Nivel, Stock y Uso).
B30: 7. Hoja Comparativa: fichas de los 14 tipos de cámara con un modelo de referencia por nivel (premium / medio / económico).

Sheet Resumen
B2: Resumen — Cobertura Marca × Tipo y Estadísticas de Equipamiento
B5: Tipo de Cámara \ Marca | C5: Axis Communications | D5: Bosch Security Systems | E5: Hanwha Vision (Wisenet) | F5: Avigilon (Motorola) | G5: Pelco (Motorola) | H5: Honeywell Security | I5: MOBOTIX | J5: Vivotek | K5: IDIS | L5: Verkada | M5: Ubiquiti (UniFi Protect) | N5: Hikvision | O5: Dahua Technology | P5: Uniview (UNV) | Q5: HiLook (Hikvision) | R5: Imou (Dahua) | S5: EZVIZ (Hikvision) | T5: Reolink | U5: TP-Link VIGI | V5: Tenda Security | W5: Total
B6: Domo | C6: =COUNTIFS('Base de Datos'!$C$5:$C$972,C$5,'Base de Datos'!$F$5:$F$972,$B6,'Base de Datos'!$G$5:$G$972,"<>*No disponible*") -> 5 | D6: =COUNTIFS('Base de Datos'!$C$5:$C$972,D$5,'Base de Datos'!$F$5:$F$972,$B6,'Base de Datos'!$G$5:$G$972,"<>*No disponible*") -> 5 | E6: =COUNTIFS('Base de Datos'!$C$5:$C$972,E$5,'Base de Datos'!$F$5:$F$972,$B6,'Base de Datos'!$G$5:$G$972,"<>*No disponible*") -> 5 | F6: =COUNTIFS('Base de Datos'!$C$5:$C$972,F$5,'Base de Datos'!$F$5:$F$972,$B6,'Base de Datos'!$G$5:$G$972,"<>*No disponible*") -> 5 | G6: =COUNTIFS('Base de Datos'!$C$5:$C$972,G$5,'Base de Datos'!$F$5:$F$972,$B6,'Base de Datos'!$G$5:$G$972,"<>*No disponible*") -> 5 | H6: =COUNTIFS('Base de Datos'!$C$5:$C$972,H$5,'Base de Datos'!$F$5:$F$972,$B6,'Base de Datos'!$G$5:$G$972,"<>*No disponible*") -> 5 | I6: =COUNTIFS('Base de Datos'!$C$5:$C$972,I$5,'Base de Datos'!$F$5:$F$972,$B6,'Base de Datos'!$G$5:$G$972,"<>*No disponible*") -> 5 | J6: =COUNTIFS('Base de Datos'!$C$5:$C$972,J$5,'Base de Datos'!$F$5:$F$972,$B6,'Base de Datos'!$G$5:$G$972,"<>*No disponible*") -> 5 | ... V6: =COUNTIFS('Base de Datos'!$C$5:$C$972,V$5,'Base de Datos'!$F$5:$F$972,$B6,'Base de Datos'!$G$5:$G$972,"<>*No disponible*") -> 5 | W6: =SUM(C6:V6) -> 100
B7: Domo Antivandálica | C7: =COUNTIFS('Base de Datos'!$C$5:$C$972,C$5,'Base de Datos'!$F$5:$F$972,$B7,'Base de Datos'!$G$5:$G$972,"<>*No disponible*") -> 5 | D7: =COUNTIFS('Base de Datos'!$C$5:$C$972,D$5,'Base de Datos'!$F$5:$F$972,$B7,'Base de Datos'!$G$5:$G$972,"<>*No disponible*") -> 5 | E7: =COUNTIFS('Base de Datos'!$C$5:$C$972,E$5,'Base de Datos'!$F$5:$F$972,$B7,'Base de Datos'!$G$5:$G$972,"<>*No disponible*") -> 5 | F7: =COUNTIFS('Base de Datos'!$C$5:$C$972,F$5,'Base de Datos'!$F$5:$F$972,$B7,'Base de Datos'!$G$5:$G$972,"<>*No disponible*") -> 5 | G7: =COUNTIFS('Base de Datos'!$C$5:$C$972,G$5,'Base de Datos'!$F$5:$F$972,$B7,'Base de Datos'!$G$5:$G$972,"<>*No disponible*") -> 5 | H7: =COUNTIFS('Base de Datos'!$C$5:$C$972,H$5,'Base de Datos'!$F$5:$F$972,$B7,'Base de Datos'!$G$5:$G$972,"<>*No disponible*") -> 5 | I7: =COUNTIFS('Base de Datos'!$C$5:$C$972,I$5,'Base de Datos'!$F$5:$F$972,$B7,'Base de Datos'!$G$5:$G$972,"<>*No disponible*") -> 5 | J7: =COUNTIFS('Base de Datos'!$C$5:$C$972,J$5,'Base de Datos'!$F$5:$F$972,$B7,'Base de Datos'!$G$5:$G$972,"<>*No disponible*") -> 5 | ... V7: =COUNTIFS('Base de Datos'!$C$5:$C$972,V$5,'Base de Datos'!$F$5:$F$972,$B7,'Base de Datos'!$G$5:$G$972,"<>*No disponible*") -> 0 | W7: =SUM(C7:V7) -> 80
B8: Bala | C8: =COUNTIFS('Base de Datos'!$C$5:$C$972,C$5,'Base de Datos'!$F$5:$F$972,$B8,'Base de Datos'!$G$5:$G$972,"<>*No disponible*") -> 5 | D8: =COUNTIFS('Base de Datos'!$C$5:$C$972,D$5,'Base de Datos'!$F$5:$F$972,$B8,'Base de Datos'!$G$5:$G$972,"<>*No disponible*") -> 5 | E8: =COUNTIFS('Base de Datos'!$C$5:$C$972,E$5,'Base de Datos'!$F$5:$F$972,$B8,'Base de Datos'!$G$5:$G$972,"<>*No disponible*") -> 5 | F8: =COUNTIFS('Base de Datos'!$C$5:$C$972,F$5,'Base de Datos'!$F$5:$F$972,$B8,'Base de Datos'!$G$5:$G$972,"<>*No disponible*") -> 5 | G8: =COUNTIFS('Base de Datos'!$C$5:$C$972,G$5,'Base de Datos'!$F$5:$F$972,$B8,'Base de Datos'!$G$5:$G$972,"<>*No disponible*") -> 5 | H8: =COUNTIFS('Base de Datos'!$C$5:$C$972,H$5,'Base de Datos'!$F$5:$F$972,$B8,'Base de Datos'!$G$5:$G$972,"<>*No disponible*") -> 5 | I8: =COUNTIFS('Base de Datos'!$C$5:$C$972,I$5,'Base de Datos'!$F$5:$F$972,$B8,'Base de Datos'!$G$5:$G$972,"<>*No disponible*") -> 5 | J8: =COUNTIFS('Base de Datos'!$C$5:$C$972,J$5,'Base de Datos'!$F$5:$F$972,$B8,'Base de Datos'!$G$5:$G$972,"<>*No disponible*") -> 5 | ... V8: =COUNTIFS('Base de Datos'!$C$5:$C$972,V$5,'Base de Datos'!$F$5:$F$972,$B8,'Base de Datos'!$G$5:$G$972,"<>*No disponible*") -> 5 | W8: =SUM(C8:V8) -> 100
B9: PTZ | C9: =COUNTIFS('Base de Datos'!$C$5:$C$972,C$5,'Base de Datos'!$F$5:$F$972,$B9,'Base de Datos'!$G$5:$G$972,"<>*No disponible*") -> 5 | D9: =COUNTIFS('Base de Datos'!$C$5:$C$972,D$5,'Base de Datos'!$F$5:$F$972,$B9,'Base de Datos'!$G$5:$G$972,"<>*No disponible*") -> 5 | E9: =COUNTIFS('Base de Datos'!$C$5:$C$972,E$5,'Base de Datos'!$F$5:$F$972,$B9,'Base de Datos'!$G$5:$G$972,"<>*No disponible*") -> 5 | F9: =COUNTIFS('Base de Datos'!$C$5:$C$972,F$5,'Base de Datos'!$F$5:$F$972,$B9,'Base de Datos'!$G$5:$G$972,"<>*No disponible*") -> 5 | G9: =COUNTIFS('Base de Datos'!$C$5:$C$972,G$5,'Base de Datos'!$F$5:$F$972,$B9,'Base de Datos'!$G$5:$G$972,"<>*No disponible*") -> 5 | H9: =COUNTIFS('Base de Datos'!$C$5:$C$972,H$5,'Base de Datos'!$F$5:$F$972,$B9,'Base de Datos'!$G$5:$G$972,"<>*No disponible*") -> 5 | I9: =COUNTIFS('Base de Datos'!$C$5:$C$972,I$5,'Base de Datos'!$F$5:$F$972,$B9,'Base de Datos'!$G$5:$G$972,"<>*No disponible*") -> 5 | J9: =COUNTIFS('Base de Datos'!$C$5:$C$972,J$5,'Base de Datos'!$F$5:$F$972,$B9,'Base de Datos'!$G$5:$G$972,"<>*No disponible*") -> 5 | ... V9: =COUNTIFS('Base de Datos'!$C$5:$C$972,V$5,'Base de Datos'!$F$5:$F$972,$B9,'Base de Datos'!$G$5:$G$972,"<>*No disponible*") -> 5 | W9: =SUM(C9:V9) -> 90
B10: Mini PTZ | C10: =COUNTIFS('Base de Datos'!$C$5:$C$972,C$5,'Base de Datos'!$F$5:$F$972,$B10,'Base de Datos'!$G$5:$G$972,"<>*No disponible*") -> 5 | D10: =COUNTIFS('Base de Datos'!$C$5:$C$972,D$5,'Base de Datos'!$F$5:$F$972,$B10,'Base de Datos'!$G$5:$G$972,"<>*No disponible*") -> 5 | E10: =COUNTIFS('Base de Datos'!$C$5:$C$972,E$5,'Base de Datos'!$F$5:$F$972,$B10,'Base de Datos'!$G$5:$G$972,"<>*No disponible*") -> 5 | F10: =COUNTIFS('Base de Datos'!$C$5:$C$972,F$5,'Base de Datos'!$F$5:$F$972,$B10,'Base de Datos'!$G$5:$G$972,"<>*No disponible*") -> 0 | G10: =COUNTIFS('Base de Datos'!$C$5:$C$972,G$5,'Base de Datos'!$F$5:$F$972,$B10,'Base de Datos'!$G$5:$G$972,"<>*No disponible*") -> 5 | H10: =COUNTIFS('Base de Datos'!$C$5:$C$972,H$5,'Base de Datos'!$F$5:$F$972,$B10,'Base de Datos'!$G$5:$G$972,"<>*No disponible*") -> 0 | I10: =COUNTIFS('Base de Datos'!$C$5:$C$972,I$5,'Base de Datos'!$F$5:$F$972,$B10,'Base de Datos'!$G$5:$G$972,"<>*No disponible*") -> 0 | J10: =COUNTIFS('Base de Datos'!$C$5:$C$972,J$5,'Base de Datos'!$F$5:$F$972,$B10,'Base de Datos'!$G$5:$G$972,"<>*No disponible*") -> 5 | ... V10: =COUNTIFS('Base de Datos'!$C$5:$C$972,V$5,'Base de Datos'!$F$5:$F$972,$B10,'Base de Datos'!$G$5:$G$972,"<>*No disponible*") -> 0 | W10: =SUM(C10:V10) -> 40
B11: Turrón (Box) | C11: =COUNTIFS('Base de Datos'!$C$5:$C$972,C$5,'Base de Datos'!$F$5:$F$972,$B11,'Base de Datos'!$G$5:$G$972,"<>*No disponible*") -> 5 | D11: =COUNTIFS('Base de Datos'!$C$5:$C$972,D$5,'Base de Datos'!$F$5:$F$972,$B11,'Base de Datos'!$G$5:$G$972,"<>*No disponible*") -> 5 | E11: =COUNTIFS('Base de Datos'!$C$5:$C$972,E$5,'Base de Datos'!$F$5:$F$972,$B11,'Base de Datos'!$G$5:$G$972,"<>*No disponible*") -> 5 | F11: =COUNTIFS('Base de Datos'!$C$5:$C$972,F$5,'Base de Datos'!$F$5:$F$972,$B11,'Base de Datos'!$G$5:$G$972,"<>*No disponible*") -> 0 | G11: =COUNTIFS('Base de Datos'!$C$5:$C$972,G$5,'Base de Datos'!$F$5:$F$972,$B11,'Base de Datos'!$G$5:$G$972,"<>*No disponible*") -> 0 | H11: =COUNTIFS('Base de Datos'!$C$5:$C$972,H$5,'Base de Datos'!$F$5:$F$972,$B11,'Base de Datos'!$G$5:$G$972,"<>*No disponible*") -> 5 | I11: =COUNTIFS('Base de Datos'!$C$5:$C$972,I$5,'Base de Datos'!$F$5:$F$972,$B11,'Base de Datos'!$G$5:$G$972,"<>*No disponible*") -> 5 | J11: =COUNTIFS('Base de Datos'!$C$5:$C$972,J$5,'Base de Datos'!$F$5:$F$972,$B11,'Base de Datos'!$G$5:$G$972,"<>*No disponible*") -> 5 | ... V11: =COUNTIFS('Base de Datos'!$C$5:$C$972,V$5,'Base de Datos'!$F$5:$F$972,$B11,'Base de Datos'!$G$5:$G$972,"<>*No disponible*") -> 0 | W11: =SUM(C11:V11) -> 40
B12: Ojo de Pez (Fisheye) | C12: =COUNTIFS('Base de Datos'!$C$5:$C$972,C$5,'Base de Datos'!$F$5:$F$972,$B12,'Base de Datos'!$G$5:$G$972,"<>*No disponible*") -> 5 | D12: =COUNTIFS('Base de Datos'!$C$5:$C$972,D$5,'Base de Datos'!$F$5:$F$972,$B12,'Base de Datos'!$G$5:$G$972,"<>*No disponible*") -> 5 | E12: =COUNTIFS('Base de Datos'!$C$5:$C$972,E$5,'Base de Datos'!$F$5:$F$972,$B12,'Base de Datos'!$G$5:$G$972,"<>*No disponible*") -> 5 | F12: =COUNTIFS('Base de Datos'!$C$5:$C$972,F$5,'Base de Datos'!$F$5:$F$972,$B12,'Base de Datos'!$G$5:$G$972,"<>*No disponible*") -> 5 | G12: =COUNTIFS('Base de Datos'!$C$5:$C$972,G$5,'Base de Datos'!$F$5:$F$972,$B12,'Base de Datos'!$G$5:$G$972,"<>*No disponible*") -> 5 | H12: =COUNTIFS('Base de Datos'!$C$5:$C$972,H$5,'Base de Datos'!$F$5:$F$972,$B12,'Base de Datos'!$G$5:$G$972,"<>*No disponible*") -> 0 | I12: =COUNTIFS('Base de Datos'!$C$5:$C$972,I$5,'Base de Datos'!$F$5:$F$972,$B12,'Base de Datos'!$G$5:$G$972,"<>*No disponible*") -> 5 | J12: =COUNTIFS('Base de Datos'!$C$5:$C$972,J$5,'Base de Datos'!$F$5:$F$972,$B12,'Base de Datos'!$G$5:$G$972,"<>*No disponible*") -> 5 | ... V12: =COUNTIFS('Base de Datos'!$C$5:$C$972,V$5,'Base de Datos'!$F$5:$F$972,$B12,'Base de Datos'!$G$5:$G$972,"<>*No disponible*") -> 0 | W12: =SUM(C12:V12) -> 65
B13: Multisensor / Panorámica | C13: =COUNTIFS('Base de Datos'!$C$5:$C$972,C$5,'Base de Datos'!$F$5:$F$972,$B13,'Base de Datos'!$G$5:$G$972,"<>*No disponible*") -> 5 | D13: =COUNTIFS('Base de Datos'!$C$5:$C$972,D$5,'Base de Datos'!$F$5:$F$972,$B13,'Base de Datos'!$G$5:$G$972,"<>*No disponible*") -> 5 | E13: =COUNTIFS('Base de Datos'!$C$5:$C$972,E$5,'Base de Datos'!$F$5:$F$972,$B13,'Base de Datos'!$G$5:$G$972,"<>*No disponible*") -> 5 | F13: =COUNTIFS('Base de Datos'!$C$5:$C$972,F$5,'Base de Datos'!$F$5:$F$972,$B13,'Base de Datos'!$G$5:$G$972,"<>*No disponible*") -> 5 | G13: =COUNTIFS('Base de Datos'!$C$5:$C$972,G$5,'Base de Datos'!$F$5:$F$972,$B13,'Base de Datos'!$G$5:$G$972,"<>*No disponible*") -> 5 | H13: =COUNTIFS('Base de Datos'!$C$5:$C$972,H$5,'Base de Datos'!$F$5:$F$972,$B13,'Base de Datos'!$G$5:$G$972,"<>*No disponible*") -> 0 | I13: =COUNTIFS('Base de Datos'!$C$5:$C$972,I$5,'Base de Datos'!$F$5:$F$972,$B13,'Base de Datos'!$G$5:$G$972,"<>*No disponible*") -> 5 | J13: =COUNTIFS('Base de Datos'!$C$5:$C$972,J$5,'Base de Datos'!$F$5:$F$972,$B13,'Base de Datos'!$G$5:$G$972,"<>*No disponible*") -> 5 | ... V13: =COUNTIFS('Base de Datos'!$C$5:$C$972,V$5,'Base de Datos'!$F$5:$F$972,$B13,'Base de Datos'!$G$5:$G$972,"<>*No disponible*") -> 0 | W13: =SUM(C13:V13) -> 45
B14: Oculta (Pinhole) | C14: =COUNTIFS('Base de Datos'!$C$5:$C$972,C$5,'Base de Datos'!$F$5:$F$972,$B14,'Base de Datos'!$G$5:$G$972,"<>*No disponible*") -> 5 | D14: =COUNTIFS('Base de Datos'!$C$5:$C$972,D$5,'Base de Datos'!$F$5:$F$972,$B14,'Base de Datos'!$G$5:$G$972,"<>*No disponible*") -> 0 | E14: =COUNTIFS('Base de Datos'!$C$5:$C$972,E$5,'Base de Datos'!$F$5:$F$972,$B14,'Base de Datos'!$G$5:$G$972,"<>*No disponible*") -> 0 | F14: =COUNTIFS('Base de Datos'!$C$5:$C$972,F$5,'Base de Datos'!$F$5:$F$972,$B14,'Base de Datos'!$G$5:$G$972,"<>*No disponible*") -> 0 | G14: =COUNTIFS('Base de Datos'!$C$5:$C$972,G$5,'Base de Datos'!$F$5:$F$972,$B14,'Base de Datos'!$G$5:$G$972,"<>*No disponible*") -> 0 | H14: =COUNTIFS('Base de Datos'!$C$5:$C$972,H$5,'Base de Datos'!$F$5:$F$972,$B14,'Base de Datos'!$G$5:$G$972,"<>*No disponible*") -> 0 | I14: =COUNTIFS('Base de Datos'!$C$5:$C$972,I$5,'Base de Datos'!$F$5:$F$972,$B14,'Base de Datos'!$G$5:$G$972,"<>*No disponible*") -> 0 | J14: =COUNTIFS('Base de Datos'!$C$5:$C$972,J$5,'Base de Datos'!$F$5:$F$972,$B14,'Base de Datos'!$G$5:$G$972,"<>*No disponible*") -> 0 | ... V14: =COUNTIFS('Base de Datos'!$C$5:$C$972,V$5,'Base de Datos'!$F$5:$F$972,$B14,'Base de Datos'!$G$5:$G$972,"<>*No disponible*") -> 0 | W14: =SUM(C14:V14) -> 15
B15: Térmica | C15: =COUNTIFS('Base de Datos'!$C$5:$C$972,C$5,'Base de Datos'!$F$5:$F$972,$B15,'Base de Datos'!$G$5:$G$972,"<>*No disponible*") -> 5 | D15: =COUNTIFS('Base de Datos'!$C$5:$C$972,D$5,'Base de Datos'!$F$5:$F$972,$B15,'Base de Datos'!$G$5:$G$972,"<>*No disponible*") -> 5 | E15: =COUNTIFS('Base de Datos'!$C$5:$C$972,E$5,'Base de Datos'!$F$5:$F$972,$B15,'Base de Datos'!$G$5:$G$972,"<>*No disponible*") -> 5 | F15: =COUNTIFS('Base de Datos'!$C$5:$C$972,F$5,'Base de Datos'!$F$5:$F$972,$B15,'Base de Datos'!$G$5:$G$972,"<>*No disponible*") -> 5 | G15: =COUNTIFS('Base de Datos'!$C$5:$C$972,G$5,'Base de Datos'!$F$5:$F$972,$B15,'Base de Datos'!$G$5:$G$972,"<>*No disponible*") -> 5 | H15: =COUNTIFS('Base de Datos'!$C$5:$C$972,H$5,'Base de Datos'!$F$5:$F$972,$B15,'Base de Datos'!$G$5:$G$972,"<>*No disponible*") -> 0 | I15: =COUNTIFS('Base de Datos'!$C$5:$C$972,I$5,'Base de Datos'!$F$5:$F$972,$B15,'Base de Datos'!$G$5:$G$972,"<>*No disponible*") -> 5 | J15: =COUNTIFS('Base de Datos'!$C$5:$C$972,J$5,'Base de Datos'!$F$5:$F$972,$B15,'Base de Datos'!$G$5:$G$972,"<>*No disponible*") -> 5 | ... V15: =COUNTIFS('Base de Datos'!$C$5:$C$972,V$5,'Base de Datos'!$F$5:$F$972,$B15,'Base de Datos'!$G$5:$G$972,"<>*No disponible*") -> 0 | W15: =SUM(C15:V15) -> 45
B16: LPR (Matrículas) | C16: =COUNTIFS('Base de Datos'!$C$5:$C$972,C$5,'Base de Datos'!$F$5:$F$972,$B16,'Base de Datos'!$G$5:$G$972,"<>*No disponible*") -> 5 | D16: =COUNTIFS('Base de Datos'!$C$5:$C$972,D$5,'Base de Datos'!$F$5:$F$972,$B16,'Base de Datos'!$G$5:$G$972,"<>*No disponible*") -> 5 | E16: =COUNTIFS('Base de Datos'!$C$5:$C$972,E$5,'Base de Datos'!$F$5:$F$972,$B16,'Base de Datos'!$G$5:$G$972,"<>*No disponible*") -> 5 | F16: =COUNTIFS('Base de Datos'!$C$5:$C$972,F$5,'Base de Datos'!$F$5:$F$972,$B16,'Base de Datos'!$G$5:$G$972,"<>*No disponible*") -> 5 | G16: =COUNTIFS('Base de Datos'!$C$5:$C$972,G$5,'Base de Datos'!$F$5:$F$972,$B16,'Base de Datos'!$G$5:$G$972,"<>*No disponible*") -> 0 | H16: =COUNTIFS('Base de Datos'!$C$5:$C$972,H$5,'Base de Datos'!$F$5:$F$972,$B16,'Base de Datos'!$G$5:$G$972,"<>*No disponible*") -> 0 | I16: =COUNTIFS('Base de Datos'!$C$5:$C$972,I$5,'Base de Datos'!$F$5:$F$972,$B16,'Base de Datos'!$G$5:$G$972,"<>*No disponible*") -> 0 | J16: =COUNTIFS('Base de Datos'!$C$5:$C$972,J$5,'Base de Datos'!$F$5:$F$972,$B16,'Base de Datos'!$G$5:$G$972,"<>*No disponible*") -> 5 | ... V16: =COUNTIFS('Base de Datos'!$C$5:$C$972,V$5,'Base de Datos'!$F$5:$F$972,$B16,'Base de Datos'!$G$5:$G$972,"<>*No disponible*") -> 0 | W16: =SUM(C16:V16) -> 50
B17: Dual-Lente | C17: =COUNTIFS('Base de Datos'!$C$5:$C$972,C$5,'Base de Datos'!$F$5:$F$972,$B17,'Base de Datos'!$G$5:$G$972,"<>*No disponible*") -> 5 | D17: =COUNTIFS('Base de Datos'!$C$5:$C$972,D$5,'Base de Datos'!$F$5:$F$972,$B17,'Base de Datos'!$G$5:$G$972,"<>*No disponible*") -> 0 | E17: =COUNTIFS('Base de Datos'!$C$5:$C$972,E$5,'Base de Datos'!$F$5:$F$972,$B17,'Base de Datos'!$G$5:$G$972,"<>*No disponible*") -> 5 | F17: =COUNTIFS('Base de Datos'!$C$5:$C$972,F$5,'Base de Datos'!$F$5:$F$972,$B17,'Base de Datos'!$G$5:$G$972,"<>*No disponible*") -> 0 | G17: =COUNTIFS('Base de Datos'!$C$5:$C$972,G$5,'Base de Datos'!$F$5:$F$972,$B17,'Base de Datos'!$G$5:$G$972,"<>*No disponible*") -> 0 | H17: =COUNTIFS('Base de Datos'!$C$5:$C$972,H$5,'Base de Datos'!$F$5:$F$972,$B17,'Base de Datos'!$G$5:$G$972,"<>*No disponible*") -> 0 | I17: =COUNTIFS('Base de Datos'!$C$5:$C$972,I$5,'Base de Datos'!$F$5:$F$972,$B17,'Base de Datos'!$G$5:$G$972,"<>*No disponible*") -> 5 | J17: =COUNTIFS('Base de Datos'!$C$5:$C$972,J$5,'Base de Datos'!$F$5:$F$972,$B17,'Base de Datos'!$G$5:$G$972,"<>*No disponible*") -> 0 | ... V17: =COUNTIFS('Base de Datos'!$C$5:$C$972,V$5,'Base de Datos'!$F$5:$F$972,$B17,'Base de Datos'!$G$5:$G$972,"<>*No disponible*") -> 0 | W17: =SUM(C17:V17) -> 45
... B19: Interior WiFi | C19: =COUNTIFS('Base de Datos'!$C$5:$C$972,C$5,'Base de Datos'!$F$5:$F$972,$B19,'Base de Datos'!$G$5:$G$972,"<>*No disponible*") -> 0 | D19: =COUNTIFS('Base de Datos'!$C$5:$C$972,D$5,'Base de Datos'!$F$5:$F$972,$B19,'Base de Datos'!$G$5:$G$972,"<>*No disponible*") -> 5 | E19: =COUNTIFS('Base de Datos'!$C$5:$C$972,E$5,'Base de Datos'!$F$5:$F$972,$B19,'Base de Datos'!$G$5:$G$972,"<>*No disponible*") -> 5 | F19: =COUNTIFS('Base de Datos'!$C$5:$C$972,F$5,'Base de Datos'!$F$5:$F$972,$B19,'Base de Datos'!$G$5:$G$972,"<>*No disponible*") -> 0 | G19: =COUNTIFS('Base de Datos'!$C$5:$C$972,G$5,'Base de Datos'!$F$5:$F$972,$B19,'Base de Datos'!$G$5:$G$972,"<>*No disponible*") -> 0 | H19: =COUNTIFS('Base de Datos'!$C$5:$C$972,H$5,'Base de Datos'!$F$5:$F$972,$B19,'Base de Datos'!$G$5:$G$972,"<>*No disponible*") -> 5 | I19: =COUNTIFS('Base de Datos'!$C$5:$C$972,I$5,'Base de Datos'!$F$5:$F$972,$B19,'Base de Datos'!$G$5:$G$972,"<>*No disponible*") -> 0 | J19: =COUNTIFS('Base de Datos'!$C$5:$C$972,J$5,'Base de Datos'!$F$5:$F$972,$B19,'Base de Datos'!$G$5:$G$972,"<>*No disponible*") -> 0 | ... V19: =COUNTIFS('Base de Datos'!$C$5:$C$972,V$5,'Base de Datos'!$F$5:$F$972,$B19,'Base de Datos'!$G$5:$G$972,"<>*No disponible*") -> 5 | W19: =SUM(C19:V19) -> 45
B20: Modelos activos por marca | C20: =SUM(C6:C19) -> 65 | D20: =SUM(D6:D19) -> 60 | E20: =SUM(E6:E19) -> 65 | F20: =SUM(F6:F19) -> 45 | G20: =SUM(G6:G19) -> 45 | H20: =SUM(H6:H19) -> 35 | I20: =SUM(I6:I19) -> 50 | J20: =SUM(J6:J19) -> 55 | ... W20: =SUM(W6:W19) -> 860
B23: Estadísticas por marca
B24: Marca | C24: Nivel | D24: País | E24: Modelos activos | F24: Precio mín. (USD) | G24: Precio máx. (USD) | H24: Precio promedio (USD)
B25: Axis Communications | C25: Premium | D25: Suecia | E25: =COUNTIFS('Base de Datos'!$C$5:$C$972,$B25,'Base de Datos'!$G$5:$G$972,"<>*No disponible*") -> 65 | F25: =MIN('Base de Datos'!$AB$5:$AB$70) -> 260 | G25: =MAX('Base de Datos'!$AB$5:$AB$70) -> 17380 | H25: =IFERROR(ROUND(AVERAGE('Base de Datos'!$AB$5:$AB$70),0),"—") -> 2819
B26: Bosch Security Systems | C26: Premium | D26: Alemania | E26: =COUNTIFS('Base de Datos'!$C$5:$C$972,$B26,'Base de Datos'!$G$5:$G$972,"<>*No disponible*") -> 60 | F26: =MIN('Base de Datos'!$AB$71:$AB$132) -> 100 | G26: =MAX('Base de Datos'!$AB$71:$AB$132) -> 25300 | H26: =IFERROR(ROUND(AVERAGE('Base de Datos'!$AB$71:$AB$132),0),"—") -> 2731
B27: Hanwha Vision (Wisenet) | C27: Premium | D27: Corea del Sur | E27: =COUNTIFS('Base de Datos'!$C$5:$C$972,$B27,'Base de Datos'!$G$5:$G$972,"<>*No disponible*") -> 65 | F27: =MIN('Base de Datos'!$AB$133:$AB$198) -> 45 | G27: =MAX('Base de Datos'!$AB$133:$AB$198) -> 10780 | H27: =IFERROR(ROUND(AVERAGE('Base de Datos'!$AB$133:$AB$198),0),"—") -> 1635
B28: Avigilon (Motorola) | C28: Premium | D28: Canadá | E28: =COUNTIFS('Base de Datos'!$C$5:$C$972,$B28,'Base de Datos'!$G$5:$G$972,"<>*No disponible*") -> 45 | F28: =MIN('Base de Datos'!$AB$199:$AB$248) -> 360 | G28: =MAX('Base de Datos'!$AB$199:$AB$248) -> 14300 | H28: =IFERROR(ROUND(AVERAGE('Base de Datos'!$AB$199:$AB$248),0),"—") -> 2528
B29: Pelco (Motorola) | C29: Premium | D29: EE. UU. | E29: =COUNTIFS('Base de Datos'!$C$5:$C$972,$B29,'Base de Datos'!$G$5:$G$972,"<>*No disponible*") -> 45 | F29: =MIN('Base de Datos'!$AB$249:$AB$298) -> 270 | G29: =MAX('Base de Datos'!$AB$249:$AB$298) -> 12760 | H29: =IFERROR(ROUND(AVERAGE('Base de Datos'!$AB$249:$AB$298),0),"—") -> 2571
B30: Honeywell Security | C30: Premium | D30: EE. UU. | E30: =COUNTIFS('Base de Datos'!$C$5:$C$972,$B30,'Base de Datos'!$G$5:$G$972,"<>*No disponible*") -> 35 | F30: =MIN('Base de Datos'!$AB$299:$AB$340) -> 65 | G30: =MAX('Base de Datos'!$AB$299:$AB$340) -> 3080 | H30: =IFERROR(ROUND(AVERAGE('Base de Datos'!$AB$299:$AB$340),0),"—") -> 510
B31: MOBOTIX | C31: Premium | D31: Alemania | E31: =COUNTIFS('Base de Datos'!$C$5:$C$972,$B31,'Base de Datos'!$G$5:$G$972,"<>*No disponible*") -> 50 | F31: =MIN('Base de Datos'!$AB$341:$AB$394) -> 445 | G31: =MAX('Base de Datos'!$AB$341:$AB$394) -> 15180 | H31: =IFERROR(ROUND(AVERAGE('Base de Datos'!$AB$341:$AB$394),0),"—") -> 2185
B32: Vivotek | C32: Medio-Alto | D32: Taiwán | E32: =COUNTIFS('Base de Datos'!$C$5:$C$972,$B32,'Base de Datos'!$G$5:$G$972,"<>*No disponible*") -> 55 | F32: =MIN('Base de Datos'!$AB$395:$AB$452) -> 150 | G32: =MAX('Base de Datos'!$AB$395:$AB$452) -> 10560 | H32: =IFERROR(ROUND(AVERAGE('Base de Datos'!$AB$395:$AB$452),0),"—") -> 1308
B33: IDIS | C33: Medio-Alto | D33: Corea del Sur | E33: =COUNTIFS('Base de Datos'!$C$5:$C$972,$B33,'Base de Datos'!$G$5:$G$972,"<>*No disponible*") -> 35 | F33: =MIN('Base de Datos'!$AB$453:$AB$494) -> 125 | G33: =MAX('Base de Datos'!$AB$453:$AB$494) -> 2530 | H33: =IFERROR(ROUND(AVERAGE('Base de Datos'!$AB$453:$AB$494),0),"—") -> 510
B34: Verkada | C34: Premium (Cloud) | D34: EE. UU. | E34: =COUNTIFS('Base de Datos'!$C$5:$C$972,$B34,'Base de Datos'!$G$5:$G$972,"<>*No disponible*") -> 30 | F34: =MIN('Base de Datos'!$AB$495:$AB$532) -> 300 | G34: =MAX('Base de Datos'!$AB$495:$AB$532) -> 1870 | H34: =IFERROR(ROUND(AVERAGE('Base de Datos'!$AB$495:$AB$532),0),"—") -> 853
B35: Ubiquiti (UniFi Protect) | C35: Medio | D35: EE. UU. | E35: =COUNTIFS('Base de Datos'!$C$5:$C$972,$B35,'Base de Datos'!$G$5:$G$972,"<>*No disponible*") -> 30 | F35: =MIN('Base de Datos'!$AB$533:$AB$570) -> 100 | G35: =MAX('Base de Datos'!$AB$533:$AB$570) -> 1540 | H35: =IFERROR(ROUND(AVERAGE('Base de Datos'!$AB$533:$AB$570),0),"—") -> 387
B36: Hikvision | C36: Medio | D36: China | E36: =COUNTIFS('Base de Datos'!$C$5:$C$972,$B36,'Base de Datos'!$G$5:$G$972,"<>*No disponible*") -> 70 | F36: =MIN('Base de Datos'!$AB$571:$AB$640) -> 40 | G36: =MAX('Base de Datos'!$AB$571:$AB$640) -> 4180 | H36: =IFERROR(ROUND(AVERAGE('Base de Datos'!$AB$571:$AB$640),0),"—") -> 571
B37: Dahua Technology | C37: Medio | D37: China | E37: =COUNTIFS('Base de Datos'!$C$5:$C$972,$B37,'Base de Datos'!$G$5:$G$972,"<>*No disponible*") -> 70 | F37: =MIN('Base de Datos'!$AB$641:$AB$710) -> 25 | G37: =MAX('Base de Datos'!$AB$641:$AB$710) -> 2090 | H37: =IFERROR(ROUND(AVERAGE('Base de Datos'!$AB$641:$AB$710),0),"—") -> 323
B38: Uniview (UNV) | C38: Medio | D38: China | E38: =COUNTIFS('Base de Datos'!$C$5:$C$972,$B38,'Base de Datos'!$G$5:$G$972,"<>*No disponible*") -> 45 | F38: =MIN('Base de Datos'!$AB$711:$AB$760) -> 50 | G38: =MAX('Base de Datos'!$AB$711:$AB$760) -> 1520 | H38: =IFERROR(ROUND(AVERAGE('Base de Datos'!$AB$711:$AB$760),0),"—") -> 314
B39: HiLook (Hikvision) | C39: Económico | D39: China | E39: =COUNTIFS('Base de Datos'!$C$5:$C$972,$B39,'Base de Datos'!$G$5:$G$972,"<>*No disponible*") -> 20 | F39: =MIN('Base de Datos'!$AB$761:$AB$790) -> 25 | G39: =MAX('Base de Datos'!$AB$761:$AB$790) -> 170 | H39: =IFERROR(ROUND(AVERAGE('Base de Datos'!$AB$761:$AB$790),0),"—") -> 68
B40: Imou (Dahua) | C40: Económico | D40: China | E40: =COUNTIFS('Base de Datos'!$C$5:$C$972,$B40,'Base de Datos'!$G$5:$G$972,"<>*No disponible*") -> 30 | F40: =MIN('Base de Datos'!$AB$791:$AB$828) -> 25 | G40: =MAX('Base de Datos'!$AB$791:$AB$828) -> 170 | H40: =IFERROR(ROUND(AVERAGE('Base de Datos'!$AB$791:$AB$828),0),"—") -> 58
B41: EZVIZ (Hikvision) | C41: Económico | D41: China | E41: =COUNTIFS('Base de Datos'!$C$5:$C$972,$B41,'Base de Datos'!$G$5:$G$972,"<>*No disponible*") -> 30 | F41: =MIN('Base de Datos'!$AB$829:$AB$866) -> 25 | G41: =MAX('Base de Datos'!$AB$829:$AB$866) -> 195 | H41: =IFERROR(ROUND(AVERAGE('Base de Datos'!$AB$829:$AB$866),0),"—") -> 62
B42: Reolink | C42: Económico | D42: China | E42: =COUNTIFS('Base de Datos'!$C$5:$C$972,$B42,'Base de Datos'!$G$5:$G$972,"<>*No disponible*") -> 30 | F42: =MIN('Base de Datos'!$AB$867:$AB$904) -> 25 | G42: =MAX('Base de Datos'!$AB$867:$AB$904) -> 420 | H42: =IFERROR(ROUND(AVERAGE('Base de Datos'!$AB$867:$AB$904),0),"—") -> 127
B43: TP-Link VIGI | C43: Económico | D43: China | E43: =COUNTIFS('Base de Datos'!$C$5:$C$972,$B43,'Base de Datos'!$G$5:$G$972,"<>*No disponible*") -> 25 | F43: =MIN('Base de Datos'!$AB$905:$AB$938) -> 25 | G43: =MAX('Base de Datos'!$AB$905:$AB$938) -> 395 | H43: =IFERROR(ROUND(AVERAGE('Base de Datos'!$AB$905:$AB$938),0),"—") -> 104
B44: Tenda Security | C44: Económico | D44: China | E44: =COUNTIFS('Base de Datos'!$C$5:$C$972,$B44,'Base de Datos'!$G$5:$G$972,"<>*No disponible*") -> 25 | F44: =MIN('Base de Datos'!$AB$939:$AB$972) -> 25 | G44: =MAX('Base de Datos'!$AB$939:$AB$972) -> 120 | H44: =IFERROR(ROUND(AVERAGE('Base de Datos'!$AB$939:$AB$972),0),"—") -> 50
B45: TOTAL / GENERAL | E45: =SUM(E25:E44) -> 860 | F45: =MIN(F25:F44) -> 25 | G45: =MAX(G25:G44) -> 25300 | H45: =IFERROR(ROUND(AVERAGE('Base de Datos'!$AB$5:$AB$972),0),"—") -> 1193
B48: Estadísticas de equipamiento por categoría
B49: Categoría de Equipamiento | C49: Modelos | D49: Precio mín. (USD) | E49: Precio máx. (USD) | F49: Precio promedio (USD)
B50: NVR / DVR | C50: =COUNTIF(Equipamiento!$C$5:$C$66,$B50) -> 10 | D50: =MIN(Equipamiento!$O$5:$O$14) -> 119 | E50: =MAX(Equipamiento!$O$5:$O$14) -> 519 | F50: =IFERROR(ROUND(AVERAGE(Equipamiento!$O$5:$O$14),0),"—") -> 290
B51: Almacenamiento (HDD) | C51: =COUNTIF(Equipamiento!$C$5:$C$66,$B51) -> 5 | D51: =MIN(Equipamiento!$O$15:$O$19) -> 95 | E51: =MAX(Equipamiento!$O$15:$O$19) -> 189 | F51: =IFERROR(ROUND(AVERAGE(Equipamiento!$O$15:$O$19),0),"—") -> 141
B52: Switch PoE | C52: =COUNTIF(Equipamiento!$C$5:$C$66,$B52) -> 7 | D52: =MIN(Equipamiento!$O$20:$O$26) -> 79 | E52: =MAX(Equipamiento!$O$20:$O$26) -> 599 | F52: =IFERROR(ROUND(AVERAGE(Equipamiento!$O$20:$O$26),0),"—") -> 248
B53: UPS | C53: =COUNTIF(Equipamiento!$C$5:$C$66,$B53) -> 6 | D53: =MIN(Equipamiento!$O$27:$O$32) -> 79 | E53: =MAX(Equipamiento!$O$27:$O$32) -> 2999 | F53: =IFERROR(ROUND(AVERAGE(Equipamiento!$O$27:$O$32),0),"—") -> 692
B54: Monitor | C54: =COUNTIF(Equipamiento!$C$5:$C$66,$B54) -> 5 | D54: =MIN(Equipamiento!$O$33:$O$37) -> 99 | E54: =MAX(Equipamiento!$O$33:$O$37) -> 249 | F54: =IFERROR(ROUND(AVERAGE(Equipamiento!$O$33:$O$37),0),"—") -> 157
B55: Rack / Gabinete | C55: =COUNTIF(Equipamiento!$C$5:$C$66,$B55) -> 5 | D55: =MIN(Equipamiento!$O$38:$O$42) -> 179 | E55: =MAX(Equipamiento!$O$38:$O$42) -> 1149 | F55: =IFERROR(ROUND(AVERAGE(Equipamiento!$O$38:$O$42),0),"—") -> 415
B56: Cableado y Conectores | C56: =COUNTIF(Equipamiento!$C$5:$C$66,$B56) -> 6 | D56: =MIN(Equipamiento!$O$43:$O$48) -> 19 | E56: =MAX(Equipamiento!$O$43:$O$48) -> 189 | F56: =IFERROR(ROUND(AVERAGE(Equipamiento!$O$43:$O$48),0),"—") -> 81
B57: Accesorios de Instalación | C57: =COUNTIF(Equipamiento!$C$5:$C$66,$B57) -> 7 | D57: =MIN(Equipamiento!$O$49:$O$55) -> 12 | E57: =MAX(Equipamiento!$O$49:$O$55) -> 229 | F57: =IFERROR(ROUND(AVERAGE(Equipamiento!$O$49:$O$55),0),"—") -> 65
B58: Alimentación / PoE | C58: =COUNTIF(Equipamiento!$C$5:$C$66,$B58) -> 5 | D58: =MIN(Equipamiento!$O$56:$O$60) -> 19 | E58: =MAX(Equipamiento!$O$56:$O$60) -> 29 | F58: =IFERROR(ROUND(AVERAGE(Equipamiento!$O$56:$O$60),0),"—") -> 25
B59: Software VMS | C59: =COUNTIF(Equipamiento!$C$5:$C$66,$B59) -> 6 | D59: =MIN(Equipamiento!$O$61:$O$66) -> 70 | E59: =MAX(Equipamiento!$O$61:$O$66) -> 549 | F59: =IFERROR(ROUND(AVERAGE(Equipamiento!$O$61:$O$66),0),"—") -> 171
B60: TOTAL / GENERAL | C60: =SUM(C50:C59) -> 62 | D60: =MIN(D50:D59) -> 12 | E60: =MAX(E50:E59) -> 2999 | F60: =IFERROR(ROUND(AVERAGE(Equipamiento!$O$5:$O$66),0),"—") -> 233
B62: Nota: la matriz cuenta modelos activos (excluye filas «No disponible en portafolio»); cada marca × tipo activo incluye 5 variantes de gama. Celda 0 = la marca no fabrica ese tipo; en Base de Datos se sugiere el equivalente. Las estadísticas de precio de cámaras leen el bloque de filas de cada marca en la Base de Datos y las del equipamiento el bloque de cada categoría en la hoja Equipamiento; si reordena los registros, ajuste los rangos de las fórmulas.

Sheet Base de Datos
B2: Base de Datos Técnica — Cámaras CCTV (20 marcas × 14 tipos × 5 variantes)
B4: N° | C4: Marca | D4: Nivel | E4: País | F4: Tipo de Cámara | G4: Modelo | H4: Resolución (MP) | I4: Resolución Máx. | J4: Sensor | K4: Lente | L4: Visión Nocturna | M4: WDR | N4: Analíticas IA | O4: Compresión | P4: ONVIF | Q4: Audio | R4: E/S Alarma | S4: Almac. Local | T4: Protección | U4: PoE | V4: Consumo | W4: Temp. Operación | X4: Dimensiones | Y4: Peso | Z4: Certificaciones | AA4: Uso Recomendado | AB4: Precio Ref. (USD) | AC4: Proveedor | AD4: Stock | AE4: Observaciones
B5: 1 | C5: Axis Communications | D5: Premium | E5: Suecia | F5: Domo | G5: AXIS M3086-V | H5: 2 MP | I5: 1920 × 1080 | J5: 1/2.8" Sony Starvis | K5: 3–9 mm varifocal P-Iris | L5: OptimizedIR 40 m | M5: Forensic WDR | N5: AXIS Object Analytics | O5: H.265 (Zipstream) / H.264 | P5: Perfil S, T, G | Q5: E/S (según modelo) | R5: E/S (según modelo) | S5: microSD 256 GB (AXIS Surveillance) | T5: IP66 / IK10 | U5: 802.3af | V5: 12.9 W máx | W5: -30 °C a +50 °C | X5: Ø 160 × 120 mm | Y5: 1.0 kg | Z5: CE, FCC, EN 50121 | AA5: Interior/Exterior | AB5: 545 | AE5: Variante económica de la gama
B6: 2 | C6: Axis Communications | D6: Premium | E6: Suecia | F6: Domo | G6: AXIS M3206-LVE | H6: 4 MP | I6: 2560 × 1440 | J6: 1/2.8" Sony Starvis | K6: 3–9 mm varifocal P-Iris | L6: OptimizedIR 40 m | M6: Forensic WDR | N6: AXIS Object Analytics | O6: H.265 (Zipstream) / H.264 | P6: Perfil S, T, G | Q6: E/S (según modelo) | R6: E/S (según modelo) | S6: microSD 256 GB (AXIS Surveillance) | T6: IP66 / IK10 | U6: 802.3af | V6: 12.9 W máx | W6: -30 °C a +50 °C | X6: Ø 160 × 120 mm | Y6: 1.0 kg | Z6: CE, FCC, EN 50121 | AA6: Interior/Exterior | AB6: 820 | AE6: Gama de entrada
B7: 3 | C7: Axis Communications | D7: Premium | E7: Suecia | F7: Domo | G7: AXIS P3245-LVE | H7: 4 MP | I7: 2560 × 1440 | J7: 1/2.8" Sony Starvis | K7: 3–9 mm varifocal P-Iris | L7: OptimizedIR 40 m | M7: Forensic WDR | N7: AXIS Object Analytics | O7: H.265 (Zipstream) / H.264 | P7: Perfil S, T, G | Q7: E/S (según modelo) | R7: E/S (según modelo) | S7: microSD 256 GB (AXIS Surveillance) | T7: IP66 / IK10 | U7: 802.3af | V7: 12.9 W máx | W7: -30 °C a +50 °C | X7: Ø 160 × 120 mm | Y7: 1.0 kg | Z7: CE, FCC, EN 50121 | AA7: Interior/Exterior | AB7: 1090 | AE7: Starlight para baja luz
B8: 4 | C8: Axis Communications | D8: Premium | E8: Suecia | F8: Domo | G8: AXIS P3265-LVE | H8: 8 MP (4K) | I8: 3840 × 2160 | J8: 1/2.8" Sony Starvis | K8: 3–9 mm varifocal P-Iris | L8: OptimizedIR 40 m | M8: Forensic WDR | N8: AXIS Object Analytics | O8: H.265 (Zipstream) / H.264 | P8: Perfil S, T, G | Q8: E/S (según modelo) | R8: E/S (según modelo) | S8: microSD 256 GB (AXIS Surveillance) | T8: IP66 / IK10 | U8: 802.3af | V8: 12.9 W máx | W8: -30 °C a +50 °C | X8: Ø 160 × 120 mm | Y8: 1.0 kg | Z8: CE, FCC, EN 50121 | AA8: Interior/Exterior | AB8: 1635 | AE8: Resolución y rendimiento mejorados
B9: 5 | C9: Axis Communications | D9: Premium | E9: Suecia | F9: Domo | G9: AXIS P3268-LVE | H9: 8 MP (4K) | I9: 3840 × 2160 | J9: 1/2.8" Sony Starvis | K9: 3–9 mm varifocal P-Iris | L9: OptimizedIR 40 m | M9: Forensic WDR | N9: AXIS Object Analytics | O9: H.265 (Zipstream) / H.264 | P9: Perfil S, T, G | Q9: E/S (según modelo) | R9: E/S (según modelo) | S9: microSD 256 GB (AXIS Surveillance) | T9: IP66 / IK10 | U9: 802.3af | V9: 12.9 W máx | W9: -30 °C a +50 °C | X9: Ø 160 × 120 mm | Y9: 1.0 kg | Z9: CE, FCC, EN 50121 | AA9: Interior/Exterior | AB9: 2400 | AE9: Tope de gama — máxima especificación
B10: 6 | C10: Axis Communications | D10: Premium | E10: Suecia | F10: Domo Antivandálica | G10: AXIS M3206-LVE | H10: 2 MP | I10: 1920 × 1080 | J10: 1/2.8" Sony Starvis | K10: 3–9 mm varifocal | L10: IR 20 m | M10: WDR | N10: Zipstream + analíticas básicas | O10: H.265 (Zipstream) / H.264 | P10: Perfil S, T, G | Q10: E/S (según modelo) | R10: E/S (según modelo) | S10: microSD 256 GB (AXIS Surveillance) | T10: IP66 / IK10 | U10: 802.3af | V10: 7.5 W máx | W10: -30 °C a +50 °C | X10: Ø 149 × 110 mm | Y10: 850 g | Z10: CE, FCC, EN 50121 | AA10: Interior/Exterior | AB10: 345 | AE10: Variante económica de la gama
B11: 7 | C11: Axis Communications | D11: Premium | E11: Suecia | F11: Domo Antivandálica | G11: AXIS P3245-LVE | H11: 4 MP | I11: 2560 × 1440 | J11: 1/2.8" Sony Starvis | K11: 3–9 mm varifocal | L11: IR 20 m | M11: WDR | N11: Zipstream + analíticas básicas | O11: H.265 (Zipstream) / H.264 | P11: Perfil S, T, G | Q11: E/S (según modelo) | R11: E/S (según modelo) | S11: microSD 256 GB (AXIS Surveillance) | T11: IP66 / IK10 | U11: 802.3af | V11: 7.5 W máx | W11: -30 °C a +50 °C | X11: Ø 149 × 110 mm | Y11: 850 g | Z11: CE, FCC, EN 50121 | AA11: Interior/Exterior | AB11: 520 | AE11: Gama de entrada
B12: 8 | C12: Axis Communications | D12: Premium | E12: Suecia | F12: Domo Antivandálica | G12: AXIS P3265-LVE | H12: 4 MP | I12: 2560 × 1440 | J12: 1/2.8" Sony Starvis | K12: 3–9 mm varifocal | L12: IR 20 m | M12: WDR | N12: Zipstream + analíticas básicas | O12: H.265 (Zipstream) / H.264 | P12: Perfil S, T, G | Q12: E/S (según modelo) | R12: E/S (según modelo) | S12: microSD 256 GB (AXIS Surveillance) | T12: IP66 / IK10 | U12: 802.3af | V12: 7.5 W máx | W12: -30 °C a +50 °C | X12: Ø 149 × 110 mm | Y12: 850 g | Z12: CE, FCC, EN 50121 | AA12: Interior/Exterior | AB12: 690 | AE12: Montaje antivandálico
B13: 9 | C13: Axis Communications | D13: Premium | E13: Suecia | F13: Domo Antivandálica | G13: AXIS Q3511-LVE | H13: 8 MP (4K) | I13: 3840 × 2160 | J13: 1/2.8" Sony Starvis | K13: 3–9 mm varifocal | L13: IR 20 m | M13: WDR | N13: Zipstream + analíticas básicas | O13: H.265 (Zipstream) / H.264 | P13: Perfil S, T, G | Q13: E/S (según modelo) | R13: E/S (según modelo) | S13: microSD 256 GB (AXIS Surveillance) | T13: IP66 / IK10 | U13: 802.3af | V13: 7.5 W máx | W13: -30 °C a +50 °C | X13: Ø 149 × 110 mm | Y13: 850 g | Z13: CE, FCC, EN 50121 | AA13: Interior/Exterior | AB13: 1035 | AE13: Resolución y rendimiento mejorados
B14: 10 | C14: Axis Communications | D14: Premium | E14: Suecia | F14: Domo Antivandálica | G14: AXIS Q3536-SLVE | H14: 8 MP (4K) | I14: 3840 × 2160 | J14: 1/2.8" Sony Starvis | K14: 3–9 mm varifocal | L14: IR 20 m | M14: WDR | N14: Zipstream + analíticas básicas | O14: H.265 (Zipstream) / H.264 | P14: Perfil S, T, G | Q14: E/S (según modelo) | R14: E/S (según modelo) | S14: microSD 256 GB (AXIS Surveillance) | T14: IP66 / IK10 | U14: 802.3af | V14: 7.5 W máx | W14: -30 °C a +50 °C | X14: Ø 149 × 110 mm | Y14: 850 g | Z14: CE, FCC, EN 50121 | AA14: Interior/Exterior | AB14: 1520 | AE14: Tope de gama — máxima especificación
B15: 11 | C15: Axis Communications | D15: Premium | E15: Suecia | F15: Bala | G15: AXIS M1135 | H15: 2 MP | I15: 1920 × 1080 | J15: 1/2.8" Sony Starvis | K15: 3–9 mm varifocal | L15: OptimizedIR 50 m | M15: Forensic WDR | N15: AXIS Object Analytics | O15: H.265 (Zipstream) / H.264 | P15: Perfil S, T, G | Q15: E/S (según modelo) | R15: E/S (según modelo) | S15: microSD 256 GB (AXIS Surveillance) | T15: IP66 / IK09 | U15: 802.3af | V15: 11.5 W máx | W15: -30 °C a +50 °C | X15: 265 × 96 × 86 mm | Y15: 950 g | Z15: CE, FCC, EN 50121 | AA15: Exterior | AB15: 470 | AE15: Variante económica de la gama
B16: 12 | C16: Axis Communications | D16: Premium | E16: Suecia | F16: Bala | G16: AXIS P1465-LE | H16: 4 MP | I16: 2560 × 1440 | J16: 1/2.8" Sony Starvis | K16: 3–9 mm varifocal | L16: OptimizedIR 50 m | M16: Forensic WDR | N16: AXIS Object Analytics | O16: H.265 (Zipstream) / H.264 | P16: Perfil S, T, G | Q16: E/S (según modelo) | R16: E/S (según modelo) | S16: microSD 256 GB (AXIS Surveillance) | T16: IP66 / IK09 | U16: 802.3af | V16: 11.5 W máx | W16: -30 °C a +50 °C | X16: 265 × 96 × 86 mm | Y16: 950 g | Z16: CE, FCC, EN 50121 | AA16: Exterior | AB16: 705 | AE16: Gama de entrada
... B69: 65 | C69: Axis Communications | D69: Premium | E69: Suecia | F69: IA Integrada | G69: AXIS Q1798-LE | H69: 8 MP (4K) | I69: 3840 × 2160 | J69: 1/2.8" Sony Starvis | K69: 3–9 mm varifocal | L69: OptimizedIR 50 m | M69: Forensic WDR | N69: ARTPEC-8 — Object Analytics (personas/vehículos) | O69: H.265 (Zipstream) / H.264 | P69: Perfil S, T, G | Q69: E/S (según modelo) | R69: E/S (según modelo) | S69: microSD 256 GB (AXIS Surveillance) | T69: IP66 / IK09 | U69: 802.3at | V69: 25 W máx | W69: -30 °C a +50 °C | X69: 336 × 138 × 106 mm | Y69: 2.4 kg | Z69: CE, FCC, EN 50121 | AA69: Exterior | AB69: 3035 | AE69: Tope de gama — máxima especificación
B70: 66 | C70: Axis Communications | D70: Premium | E70: Suecia | F70: Interior WiFi | G70: No disponible en portafolio | AE70: AXIS no comercializa cámaras WiFi de interior; referencia PoE: AXIS M1065-L (1080p)
B71: 67 | C71: Bosch Security Systems | D71: Premium | E71: Alemania | F71: Domo | G71: FLEXIDOME IP indoor 3000i (NDI-3502-AL) | H71: 2 MP | I71: 1920 × 1080 | J71: 1/2.8" CMOS | K71: 2.8–10 mm varifocal | L71: Día/Noche — IR 20 m | M71: WDR 120 dB | N71: Analíticas Bosch (movimiento inteligente) | O71: H.265 / H.264 (Smart Encoding) | P71: Perfil S, T, G | Q71: E/S integrada | R71: 1 E / 1 S | S71: microSD 512 GB | T71: IK10 (interior) | U71: 802.3af | V71: 7 W máx | W71: -30 °C a +55 °C | X71: Ø 140 × 95 mm | Y71: 700 g | Z71: CE, FCC, UL | AA71: Interior | AB71: 390 | AE71: Variante económica de la gama
B72: 68 | C72: Bosch Security Systems | D72: Premium | E72: Alemania | F72: Domo | G72: FLEXIDOME IP indoor 3000i (NDI-3503-AL) | H72: 4 MP | I72: 2560 × 1440 | J72: 1/2.8" CMOS | K72: 2.8–10 mm varifocal | L72: Día/Noche — IR 20 m | M72: WDR 120 dB | N72: Analíticas Bosch (movimiento inteligente) | O72: H.265 / H.264 (Smart Encoding) | P72: Perfil S, T, G | Q72: E/S integrada | R72: 1 E / 1 S | S72: microSD 512 GB | T72: IK10 (interior) | U72: 802.3af | V72: 7 W máx | W72: -30 °C a +55 °C | X72: Ø 140 × 95 mm | Y72: 700 g | Z72: CE, FCC, UL | AA72: Interior | AB72: 585 | AE72: Gama de entrada
B73: 69 | C73: Bosch Security Systems | D73: Premium | E73: Alemania | F73: Domo | G73: FLEXIDOME IP indoor 5000i (NDI-5502-AL) | H73: 4 MP | I73: 2560 × 1440 | J73: 1/2.8" CMOS | K73: 2.8–10 mm varifocal | L73: Día/Noche — IR 20 m | M73: WDR 120 dB | N73: Analíticas Bosch (movimiento inteligente) | O73: H.265 / H.264 (Smart Encoding) | P73: Perfil S, T, G | Q73: E/S integrada | R73: 1 E / 1 S | S73: microSD 512 GB | T73: IK10 (interior) | U73: 802.3af | V73: 7 W máx | W73: -30 °C a +55 °C | X73: Ø 140 × 95 mm | Y73: 700 g | Z73: CE, FCC, UL | AA73: Interior | AB73: 780 | AE73: Línea 5000i con IVA básico
B74: 70 | C74: Bosch Security Systems | D74: Premium | E74: Alemania | F74: Domo | G74: FLEXIDOME IP indoor 5000i (NDI-5503-AL) | H74: 8 MP (4K) | I74: 3840 × 2160 | J74: 1/2.8" CMOS | K74: 2.8–10 mm varifocal | L74: Día/Noche — IR 20 m | M74: WDR 120 dB | N74: Analíticas Bosch (movimiento inteligente) | O74: H.265 / H.264 (Smart Encoding) | P74: Perfil S, T, G | Q74: E/S integrada | R74: 1 E / 1 S | S74: microSD 512 GB | T74: IK10 (interior) | U74: 802.3af | V74: 7 W máx | W74: -30 °C a +55 °C | X74: Ø 140 × 95 mm | Y74: 700 g | Z74: CE, FCC, UL | AA74: Interior | AB74: 1170 | AE74: Resolución y rendimiento mejorados
B75: 71 | C75: Bosch Security Systems | D75: Premium | E75: Alemania | F75: Domo | G75: FLEXIDOME IP indoor 7000i (NDI-7503-Z12) | H75: 8 MP (4K) | I75: 3840 × 2160 | J75: 1/2.8" CMOS | K75: 2.8–10 mm varifocal | L75: Día/Noche — IR 20 m | M75: WDR 120 dB | N75: Analíticas Bosch (movimiento inteligente) | O75: H.265 / H.264 (Smart Encoding) | P75: Perfil S, T, G | Q75: E/S integrada | R75: 1 E / 1 S | S75: microSD 512 GB | T75: IK10 (interior) | U75: 802.3af | V75: 7 W máx | W75: -30 °C a +55 °C | X75: Ø 140 × 95 mm | Y75: 700 g | Z75: CE, FCC, UL | AA75: Interior | AB75: 1715 | AE75: Tope de gama — máxima especificación
B76: 72 | C76: Bosch Security Systems | D76: Premium | E76: Alemania | F76: Domo Antivandálica | G76: FLEXIDOME IP outdoor 3000i (NDE-3502-AL) | H76: 2 MP | I76: 1920 × 1080 | J76: 1/2.8" CMOS | K76: 2.8–10 mm varifocal | L76: IR 30 m | M76: WDR 120 dB | N76: Analíticas Bosch (movimiento inteligente) | O76: H.265 / H.264 (Smart Encoding) | P76: Perfil S, T, G | Q76: E/S integrada | R76: 1 E / 1 S | S76: microSD 512 GB | T76: IP66 / IK10 | U76: 802.3af | V76: 9 W máx | W76: -30 °C a +55 °C | X76: Ø 140 × 100 mm | Y76: 780 g | Z76: CE, FCC, UL | AA76: Exterior | AB76: 445 | AE76: Variante económica de la gama
B77: 73 | C77: Bosch Security Systems | D77: Premium | E77: Alemania | F77: Domo Antivandálica | G77: FLEXIDOME IP outdoor 3000i (NDE-3503-AL) | H77: 4 MP | I77: 2560 × 1440 | J77: 1/2.8" CMOS | K77: 2.8–10 mm varifocal | L77: IR 30 m | M77: WDR 120 dB | N77: Analíticas Bosch (movimiento inteligente) | O77: H.265 / H.264 (Smart Encoding) | P77: Perfil S, T, G | Q77: E/S integrada | R77: 1 E / 1 S | S77: microSD 512 GB | T77: IP66 / IK10 | U77: 802.3af | V77: 9 W máx | W77: -30 °C a +55 °C | X77: Ø 140 × 100 mm | Y77: 780 g | Z77: CE, FCC, UL | AA77: Exterior | AB77: 670 | AE77: Gama de entrada
B78: 74 | C78: Bosch Security Systems | D78: Premium | E78: Alemania | F78: Domo Antivandálica | G78: FLEXIDOME IP outdoor 5000i (NDE-5502-AL) | H78: 4 MP | I78: 2560 × 1440 | J78: 1/2.8" CMOS | K78: 2.8–10 mm varifocal | L78: IR 30 m | M78: WDR 120 dB | N78: Analíticas Bosch (movimiento inteligente) | O78: H.265 / H.264 (Smart Encoding) | P78: Perfil S, T, G | Q78: E/S integrada | R78: 1 E / 1 S | S78: microSD 512 GB | T78: IP66 / IK10 | U78: 802.3af | V78: 9 W máx | W78: -30 °C a +55 °C | X78: Ø 140 × 100 mm | Y78: 780 g | Z78: CE, FCC, UL | AA78: Exterior | AB78: 890 | AE78: Antivandálica IK10
B79: 75 | C79: Bosch Security Systems | D79: Premium | E79: Alemania | F79: Domo Antivandálica | G79: FLEXIDOME IP outdoor 5000i (NDE-5503-AL) | H79: 8 MP (4K) | I79: 3840 × 2160 | J79: 1/2.8" CMOS | K79: 2.8–10 mm varifocal | L79: IR 30 m | M79: WDR 120 dB | N79: Analíticas Bosch (movimiento inteligente) | O79: H.265 / H.264 (Smart Encoding) | P79: Perfil S, T, G | Q79: E/S integrada | R79: 1 E / 1 S | S79: microSD 512 GB | T79: IP66 / IK10 | U79: 802.3af | V79: 9 W máx | W79: -30 °C a +55 °C | X79: Ø 140 × 100 mm | Y79: 780 g | Z79: CE, FCC, UL | AA79: Exterior | AB79: 1335 | AE79: Resolución y rendimiento mejorados
B80: 76 | C80: Bosch Security Systems | D80: Premium | E80: Alemania | F80: Domo Antivandálica | G80: FLEXIDOME IP outdoor 7000i (NDE-7503-Z12) | H80: 8 MP (4K) | I80: 3840 × 2160 | J80: 1/2.8" CMOS | K80: 2.8–10 mm varifocal | L80: IR 30 m | M80: WDR 120 dB | N80: Analíticas Bosch (movimiento inteligente) | O80: H.265 / H.264 (Smart Encoding) | P80: Perfil S, T, G | Q80: E/S integrada | R80: 1 E / 1 S | S80: microSD 512 GB | T80: IP66 / IK10 | U80: 802.3af | V80: 9 W máx | W80: -30 °C a +55 °C | X80: Ø 140 × 100 mm | Y80: 780 g | Z80: CE, FCC, UL | AA80: Exterior | AB80: 1960 | AE80: Tope de gama — máxima especificación
B81: 77 | C81: Bosch Security Systems | D81: Premium | E81: Alemania | F81: Bala | G81: DINION IP 3000i IR (NBE-3502-AL) | H81: 2 MP | I81: 1920 × 1080 | J81: 1/2.8" CMOS | K81: 3–10 mm varifocal | L81: IR 40 m | M81: WDR 120 dB | N81: Analíticas Bosch | O81: H.265 / H.264 (Smart Encoding) | P81: Perfil S, T, G | Q81: E/S integrada | R81: 1 E / 1 S | S81: microSD 512 GB | T81: IP66 | U81: 802.3af | V81: 9 W máx | W81: -30 °C a +55 °C | X81: 240 × 90 × 90 mm | Y81: 1.1 kg | Z81: CE, FCC, UL | AA81: Exterior | AB81: 465 | AE81: Variante económica de la gama
B82: 78 | C82: Bosch Security Systems | D82: Premium | E82: Alemania | F82: Bala | G82: DINION IP 3000i IR (NBE-3503-AL) | H82: 4 MP | I82: 2560 × 1440 | J82: 1/2.8" CMOS | K82: 3–10 mm varifocal | L82: IR 40 m | M82: WDR 120 dB | N82: Analíticas Bosch | O82: H.265 / H.264 (Smart Encoding) | P82: Perfil S, T, G | Q82: E/S integrada | R82: 1 E / 1 S | S82: microSD 512 GB | T82: IP66 | U82: 802.3af | V82: 9 W máx | W82: -30 °C a +55 °C | X82: 240 × 90 × 90 mm | Y82: 1.1 kg | Z82: CE, FCC, UL | AA82: Exterior | AB82: 700 | AE82: Gama de entrada
... B110: 106 | C110: Bosch Security Systems | D110: Premium | E110: Alemania | F110: Multisensor / Panorámica | G110: FLEXIDOME IP multi 9000i (NDS-9004-X40) | H110: 48 MP (4× 12 MP) | I110: 4× 4000 × 3000 | J110: 4× 1/2.7" CMOS | K110: 4× varifocal integrada | L110: IR 20 m | M110: WDR | N110: Multidireccional 180° + IVA | O110: H.265 / H.264 (Smart Encoding) | P110: Perfil S, T, G | Q110: E/S integrada | R110: 1 E / 1 S | S110: microSD 512 GB | T110: IP66 / IK10 | U110: 802.3at | V110: 20 W máx | W110: -30 °C a +55 °C | X110: Ø 240 × 85 mm | Y110: 1.9 kg | Z110: CE, FCC, UL | AA110: Interior/Exterior | AB110: 8580 | AE110: Tope de gama — máxima especificación
B111: 107 | C111: Bosch Security Systems | D111: Premium | E111: Alemania | F111: Oculta (Pinhole) | G111: No disponible en portafolio | AE111: Bosch no ofrece cámara oculta; alternativa micro-discreta: FLEXIDOME IP micro 5000i
B112: 108 | C112: Bosch Security Systems | D112: Premium | E112: Alemania | F112: Térmica | G112: MIC IP thermal 7100i (35 mm) | H112: Térmico 384 × 288 | I112: 384 × 288 px | J112: Microbolómetro LWIR | K112: 35/60/95 mm (según versión) | L112: Detección térmica 1.2 km | M112: — | N112: PTZ térmico + analíticas perimetrales | O112: H.265 / H.264 (Smart Encoding) | P112: Perfil S, T, G | Q112: E/S integrada | R112: 1 E / 1 S | S112: microSD 512 GB | T112: IP66 / IK10 | U112: 802.3at | V112: 65 W máx | W112: -30 °C a +55 °C | X112: Ø 245 × 545 mm | Y112: 9.5 kg | Z112: CE, FCC, UL | AA112: Exterior | AB112: 5750 | AE112: Variante económica de la gama
B113: 109 | C113: Bosch Security Systems | D113: Premium | E113: Alemania | F113: Térmica | G113: MIC IP thermal 7100i (60 mm) | H113: Térmico 384 × 288 | I113: 384 × 288 px | J113: Microbolómetro LWIR | K113: 35/60/95 mm (según versión) | L113: Detección térmica 1.2 km | M113: — | N113: PTZ térmico + analíticas perimetrales | O113: H.265 / H.264 (Smart Encoding) | P113: Perfil S, T, G | Q113: E/S integrada | R113: 1 E / 1 S | S113: microSD 512 GB | T113: IP66 / IK10 | U113: 802.3at | V113: 65 W máx | W113: -30 °C a +55 °C | X113: Ø 245 × 545 mm | Y113: 9.5 kg | Z113: CE, FCC, UL | AA113: Exterior | AB113: 8625 | AE113: Gama de entrada
B114: 110 | C114: Bosch Security Systems | D114: Premium | E114: Alemania | F114: Térmica | G114: MIC IP thermal 7100i (95 mm) | H114: Térmico 640 × 480 | I114: 640 × 480 px | J114: Microbolómetro LWIR | K114: 35/60/95 mm (según versión) | L114: Detección térmica 1.2 km | M114: — | N114: PTZ térmico + analíticas perimetrales | O114: H.265 / H.264 (Smart Encoding) | P114: Perfil S, T, G | Q114: E/S integrada | R114: 1 E / 1 S | S114: microSD 512 GB | T114: IP66 / IK10 | U114: 802.3at | V114: 65 W máx | W114: -30 °C a +55 °C | X114: Ø 245 × 545 mm | Y114: 9.5 kg | Z114: CE, FCC, UL | AA114: Exterior | AB114: 11500 | AE114: PTZ térmico rotatorio 360°
B115: 111 | C115: Bosch Security Systems | D115: Premium | E115: Alemania | F115: Térmica | G115: MIC IP dynamic 7000i | H115: Térmico 640 × 480 | I115: 640 × 480 px | J115: Microbolómetro LWIR | K115: 35/60/95 mm (según versión) | L115: Detección térmica 1.2 km | M115: — | N115: PTZ térmico + analíticas perimetrales | O115: H.265 / H.264 (Smart Encoding) | P115: Perfil S, T, G | Q115: E/S integrada | R115: 1 E / 1 S | S115: microSD 512 GB | T115: IP66 / IK10 | U115: 802.3at | V115: 65 W máx | W115: -30 °C a +55 °C | X115: Ø 245 × 545 mm | Y115: 9.5 kg | Z115: CE, FCC, UL | AA115: Exterior | AB115: 17250 | AE115: Resolución y rendimiento mejorados
B116: 112 | C116: Bosch Security Systems | D116: Premium | E116: Alemania | F116: Térmica | G116: MIC IP fusion 9000i | H116: Térmico 640 × 480 | I116: 640 × 480 px | J116: Microbolómetro LWIR | K116: 35/60/95 mm (según versión) | L116: Detección térmica 1.2 km | M116: — | N116: PTZ térmico + analíticas perimetrales | O116: H.265 / H.264 (Smart Encoding) | P116: Perfil S, T, G | Q116: E/S integrada | R116: 1 E / 1 S | S116: microSD 512 GB | T116: IP66 / IK10 | U116: 802.3at | V116: 65 W máx | W116: -30 °C a +55 °C | X116: Ø 245 × 545 mm | Y116: 9.5 kg | Z116: CE, FCC, UL | AA116: Exterior | AB116: 25300 | AE116: Tope de gama — máxima especificación
B117: 113 | C117: Bosch Security Systems | D117: Premium | E117: Alemania | F117: LPR (Matrículas) | G117: DINION 7100i IR ANPR (8–32 mm) | H117: 2 MP | I117: 1920 × 1080 | J117: 1/2.8" CMOS | K117: 8–32 mm varifocal | L117: IR 40 m — obturador rápido | M117: WDR 120 dB | N117: ANPR vía Video Analytics (licencia) | O117: H.265 / H.264 (Smart Encoding) | P117: Perfil S, T, G | Q117: E/S integrada | R117: 1 E / 1 S | S117: microSD 512 GB | T117: IP66 | U117: 802.3af | V117: 10 W máx | W117: -30 °C a +55 °C | X117: 250 × 92 × 90 mm | Y117: 1.0 kg | Z117: CE, FCC, UL | AA117: Exterior | AB117: 525 | AE117: Variante económica de la gama
B118: 114 | C118: Bosch Security Systems | D118: Premium | E118: Alemania | F118: LPR (Matrículas) | G118: DINION 7100i IR ANPR (16–50 mm) | H118: 4 MP | I118: 2560 × 1440 | J118: 1/2.8" CMOS | K118: 8–32 mm varifocal | L118: IR 40 m — obturador rápido | M118: WDR 120 dB | N118: ANPR vía Video Analytics (licencia) | O118: H.265 / H.264 (Smart Encoding) | P118: Perfil S, T, G | Q118: E/S integrada | R118: 1 E / 1 S | S118: microSD 512 GB | T118: IP66 | U118: 802.3af | V118: 10 W máx | W118: -30 °C a +55 °C | X118: 250 × 92 × 90 mm | Y118: 1.0 kg | Z118: CE, FCC, UL | AA118: Exterior | AB118: 790 | AE118: Gama de entrada
B119: 115 | C119: Bosch Security Systems | D119: Premium | E119: Alemania | F119: LPR (Matrículas) | G119: DINION 7100i IR ANPR (35–80 mm) | H119: 8 MP (4K) | I119: 3840 × 2160 | J119: 1/2.8" CMOS | K119: 8–32 mm varifocal | L119: IR 40 m — obturador rápido | M119: WDR 120 dB | N119: ANPR vía Video Analytics (licencia) | O119: H.265 / H.264 (Smart Encoding) | P119: Perfil S, T, G | Q119: E/S integrada | R119: 1 E / 1 S | S119: microSD 512 GB | T119: IP66 | U119: 802.3af | V119: 10 W máx | W119: -30 °C a +55 °C | X119: 250 × 92 × 90 mm | Y119: 1.0 kg | Z119: CE, FCC, UL | AA119: Exterior | AB119: 1050 | AE119: Lectura de matrículas con VMS
B120: 116 | C120: Bosch Security Systems | D120: Premium | E120: Alemania | F120: LPR (Matrículas) | G120: FLEXIDOME 7100i IR ANPR (8–32 mm) | H120: 8 MP (4K) | I120: 3840 × 2160 | J120: 1/2.8" CMOS | K120: 8–32 mm varifocal | L120: IR 40 m — obturador rápido | M120: WDR 120 dB | N120: ANPR vía Video Analytics (licencia) | O120: H.265 / H.264 (Smart Encoding) | P120: Perfil S, T, G | Q120: E/S integrada | R120: 1 E / 1 S | S120: microSD 512 GB | T120: IP66 | U120: 802.3af | V120: 10 W máx | W120: -30 °C a +55 °C | X120: 250 × 92 × 90 mm | Y120: 1.0 kg | Z120: CE, FCC, UL | AA120: Exterior | AB120: 1575 | AE120: Resolución y rendimiento mejorados
B121: 117 | C121: Bosch Security Systems | D121: Premium | E121: Alemania | F121: LPR (Matrículas) | G121: AUTODOME 7000i ANPR | H121: 8 MP (4K) | I121: 3840 × 2160 | J121: 1/2.8" CMOS | K121: 8–32 mm varifocal | L121: IR 40 m — obturador rápido | M121: WDR 120 dB | N121: ANPR vía Video Analytics (licencia) | O121: H.265 / H.264 (Smart Encoding) | P121: Perfil S, T, G | Q121: E/S integrada | R121: 1 E / 1 S | S121: microSD 512 GB | T121: IP66 | U121: 802.3af | V121: 10 W máx | W121: -30 °C a +55 °C | X121: 250 × 92 × 90 mm | Y121: 1.0 kg | Z121: CE, FCC, UL | AA121: Exterior | AB121: 2310 | AE121: Tope de gama — máxima especificación
B122: 118 | C122: Bosch Security Systems | D122: Premium | E122: Alemania | F122: Dual-Lente | G122: No disponible en portafolio | AE122: Sin dual-lente convencional; referencia multidireccional: FLEXIDOME IP multi 7000i
B123: 119 | C123: Bosch Security Systems | D123: Premium | E123: Alemania | F123: IA Integrada | G123: FLEXIDOME IP indoor 5000i (IVA) | H123: 2 MP | I123: 1920 × 1080 | J123: 1/2.8" CMOS | K123: 2.8–10 mm varifocal | L123: IR 30 m | M123: WDR 120 dB | N123: IVA Pro — IA en el borde (personas/vehículos) | O123: H.265 / H.264 (Smart Encoding) | P123: Perfil S, T, G | Q123: E/S integrada | R123: 1 E / 1 S | S123: microSD 512 GB | T123: IP66 / IK10 | U123: 802.3af | V123: 10 W máx | W123: -30 °C a +55 °C | X123: Ø 150 × 100 mm | Y123: 760 g | Z123: CE, FCC, UL | AA123: Interior/Exterior | AB123: 625 | AE123: Variante económica de la gama
B124: 120 | C124: Bosch Security Systems | D124: Premium | E124: Alemania | F124: IA Integrada | G124: FLEXIDOME IP outdoor 5000i (IVA) | H124: 4 MP | I124: 2560 × 1440 | J124: 1/2.8" CMOS | K124: 2.8–10 mm varifocal | L124: IR 30 m | M124: WDR 120 dB | N124: IVA Pro — IA en el borde (personas/vehículos) | O124: H.265 / H.264 (Smart Encoding) | P124: Perfil S, T, G | Q124: E/S integrada | R124: 1 E / 1 S | S124: microSD 512 GB | T124: IP66 / IK10 | U124: 802.3af | V124: 10 W máx | W124: -30 °C a +55 °C | X124: Ø 150 × 100 mm | Y124: 760 g | Z124: CE, FCC, UL | AA124: Interior/Exterior | AB124: 940 | AE124: Gama de entrada
B125: 121 | C125: Bosch Security Systems | D125: Premium | E125: Alemania | F125: IA Integrada | G125: DINION IP bullet 5000i (IVA) | H125: 4 MP | I125: 2560 × 1440 | J125: 1/2.8" CMOS | K125: 2.8–10 mm varifocal | L125: IR 30 m | M125: WDR 120 dB | N125: IVA Pro — IA en el borde (personas/vehículos) | O125: H.265 / H.264 (Smart Encoding) | P125: Perfil S, T, G | Q125: E/S integrada | R125: 1 E / 1 S | S125: microSD 512 GB | T125: IP66 / IK10 | U125: 802.3af | V125: 10 W máx | W125: -30 °C a +55 °C | X125: Ø 150 × 100 mm | Y125: 760 g | Z125: CE, FCC, UL | AA125: Interior/Exterior | AB125: 1250 | AE125: Analíticas deep learning Bosch
B126: 122 | C126: Bosch Security Systems | D126: Premium | E126: Alemania | F126: IA Integrada | G126: FLEXIDOME IP 7000i (IVA avanzado) | H126: 8 MP (4K) | I126: 3840 × 2160 | J126: 1/2.8" CMOS | K126: 2.8–10 mm varifocal | L126: IR 30 m | M126: WDR 120 dB | N126: IVA Pro — IA en el borde (personas/vehículos) | O126: H.265 / H.264 (Smart Encoding) | P126: Perfil S, T, G | Q126: E/S integrada | R126: 1 E / 1 S | S126: microSD 512 GB | T126: IP66 / IK10 | U126: 802.3af | V126: 10 W máx | W126: -30 °C a +55 °C | X126: Ø 150 × 100 mm | Y126: 760 g | Z126: CE, FCC, UL | AA126: Interior/Exterior | AB126: 1875 | AE126: Resolución y rendimiento mejorados
B127: 123 | C127: Bosch Security Systems | D127: Premium | E127: Alemania | F127: IA Integrada | G127: MIC IP fusion 9000i (IVA) | H127: 8 MP (4K) | I127: 3840 × 2160 | J127: 1/2.8" CMOS | K127: 2.8–10 mm varifocal | L127: IR 30 m | M127: WDR 120 dB | N127: IVA Pro — IA en el borde (personas/vehículos) | O127: H.265 / H.264 (Smart Encoding) | P127: Perfil S, T, G | Q127: E/S integrada | R127: 1 E / 1 S | S127: microSD 512 GB | T127: IP66 / IK10 | U127: 802.3af | V127: 10 W máx | W127: -30 °C a +55 °C | X127: Ø 150 × 100 mm | Y127: 760 g | Z127: CE, FCC, UL | AA127: Interior/Exterior | AB127: 2750 | AE127: Tope de gama — máxima especificación
B128: 124 | C128: Bosch Security Systems | D128: Premium | E128: Alemania | F128: Interior WiFi | G128: Bosch Smart Home Camera 360° | H128: 2 MP | I128: 1920 × 1080 | J128: CMOS | K128: Gran angular 180° | L128: IR 5 m | M128: — | N128: Detección de personas (app Bosch Smart Home) | O128: H.264 | P128: — (ecosistema Bosch) | Q128: Micrófono/altavoz integrado | R128: — | S128: No — grabación en Bosch Smart Home Controller | T128: Interior | U128: WiFi 2.4/5 GHz | V128: 5 W máx | W128: 0 °C a +40 °C | X128: Ø 56 × 108 mm | Y128: 210 g | Z128: CE, FCC | AA128: Interior | AB128: 100 | AE128: Variante económica de la gama
B129: 125 | C129: Bosch Security Systems | D129: Premium | E129: Alemania | F129: Interior WiFi | G129: Bosch Smart Home Camera II | H129: 2 MP | I129: 1920 × 1080 | J129: CMOS | K129: Gran angular 180° | L129: IR 5 m | M129: — | N129: Detección de personas (app Bosch Smart Home) | O129: H.264 | P129: — (ecosistema Bosch) | Q129: Micrófono/altavoz integrado | R129: — | S129: No — grabación en Bosch Smart Home Controller | T129: Interior | U129: WiFi 2.4/5 GHz | V129: 5 W máx | W129: 0 °C a +40 °C | X129: Ø 56 × 108 mm | Y129: 210 g | Z129: CE, FCC | AA129: Interior | AB129: 150 | AE129: Gama de entrada
B130: 126 | C130: Bosch Security Systems | D130: Premium | E130: Alemania | F130: Interior WiFi | G130: Bosch Smart Home Eyes II (interior) | H130: 4 MP | I130: 2560 × 1440 | J130: CMOS | K130: Gran angular 180° | L130: IR 5 m | M130: — | N130: Detección de personas (app Bosch Smart Home) | O130: H.264 | P130: — (ecosistema Bosch) | Q130: Micrófono/altavoz integrado | R130: — | S130: No — grabación en Bosch Smart Home Controller | T130: Interior | U130: WiFi 2.4/5 GHz | V130: 5 W máx | W130: 0 °C a +40 °C | X130: Ø 56 × 108 mm | Y130: 210 g | Z130: CE, FCC | AA130: Interior | AB130: 200 | AE130: Ecosistema Bosch Smart Home
B131: 127 | C131: Bosch Security Systems | D131: Premium | E131: Alemania | F131: Interior WiFi | G131: Bosch Smart Home Eyes (exterior) | H131: 4 MP | I131: 2560 × 1440 | J131: CMOS | K131: Gran angular 180° | L131: IR 5 m | M131: — | N131: Detección de personas (app Bosch Smart Home) | O131: H.264 | P131: — (ecosistema Bosch) | Q131: Micrófono/altavoz integrado | R131: — | S131: No — grabación en Bosch Smart Home Controller | T131: Interior | U131: WiFi 2.4/5 GHz | V131: 5 W máx | W131: 0 °C a +40 °C | X131: Ø 56 × 108 mm | Y131: 210 g | Z131: CE, FCC | AA131: Interior | AB131: 300 | AE131: Resolución y rendimiento mejorados
B132: 128 | C132: Bosch Security Systems | D132: Premium | E132: Alemania | F132: Interior WiFi | G132: Bosch Smart Home Eyes II (exterior) | H132: 8 MP (4K) | I132: 3840 × 2160 | J132: CMOS | K132: Gran angular 180° | L132: IR 5 m | M132: — | N132: Detección de personas (app Bosch Smart Home) | O132: H.264 | P132: — (ecosistema Bosch) | Q132: Micrófono/altavoz integrado | R132: — | S132: No — grabación en Bosch Smart Home Controller | T132: Interior | U132: WiFi 2.4/5 GHz | V132: 5 W máx | W132: 0 °C a +40 °C | X132: Ø 56 × 108 mm | Y132: 210 g | Z132: CE, FCC | AA132: Interior | AB132: 440 | AE132: Tope de gama — máxima especificación
B133: 129 | C133: Hanwha Vision (Wisenet) | D133: Premium | E133: Corea del Sur | F133: Domo | G133: XNV-6011 | H133: 2 MP | I133: 1920 × 1080 | J133: 1/2.7" CMOS | K133: 2.8 mm fijo (3.6 mm opcional) | L133: IR 20 m | M133: WDR 120 dB | N133: WiseStream III + analíticas básicas | O133: H.265 (WiseStream II) / H.264 | P133: Perfil S, T, G | Q133: E/S integrada | R133: 1 E / 1 S | S133: microSD 256 GB | T133: IP66 / IK10 | U133: 802.3af | V133: 8 W máx | W133: -30 °C a +55 °C | X133: Ø 128 × 96 mm | Y133: 600 g | Z133: CE, FCC | AA133: Interior/Exterior | AB133: 170 | AE133: Variante económica de la gama
B134: 130 | C134: Hanwha Vision (Wisenet) | D134: Premium | E134: Corea del Sur | F134: Domo | G134: XNV-6081R | H134: 4 MP | I134: 2560 × 1440 | J134: 1/2.7" CMOS | K134: 2.8 mm fijo (3.6 mm opcional) | L134: IR 20 m | M134: WDR 120 dB | N134: WiseStream III + analíticas básicas | O134: H.265 (WiseStream II) / H.264 | P134: Perfil S, T, G | Q134: E/S integrada | R134: 1 E / 1 S | S134: microSD 256 GB | T134: IP66 / IK10 | U134: 802.3af | V134: 8 W máx | W134: -30 °C a +55 °C | X134: Ø 128 × 96 mm | Y134: 600 g | Z134: CE, FCC | AA134: Interior/Exterior | AB134: 255 | AE134: Gama de entrada
... B172: 168 | C172: Hanwha Vision (Wisenet) | D172: Premium | E172: Corea del Sur | F172: Multisensor / Panorámica | G172: PNM-C34404RQPZ | H172: 48 MP (4× 12 MP) | I172: 4× 4000 × 3000 | J172: 4× 1/2.8" + 1× fisheye | K172: 4× 2.8 mm + 1× 1.05 mm | L172: IR 20 m | M172: WDR | N172: 4 cabezas direccionales + panorámica 360° | O172: H.265 (WiseStream II) / H.264 | P172: Perfil S, T, G | Q172: E/S integrada | R172: 1 E / 1 S | S172: microSD 256 GB | T172: IK10 | U172: 802.3at | V172: 30 W máx | W172: -30 °C a +55 °C | X172: Ø 330 × 95 mm | Y172: 2.6 kg | Z172: CE, FCC | AA172: Interior | AB172: 5280 | AE172: Tope de gama — máxima especificación
B173: 169 | C173: Hanwha Vision (Wisenet) | D173: Premium | E173: Corea del Sur | F173: Oculta (Pinhole) | G173: No disponible en portafolio | AE173: Hanwha no ofrece cámara oculta; alternativa discreta: domos XND compactos
B174: 170 | C174: Hanwha Vision (Wisenet) | D174: Premium | E174: Corea del Sur | F174: Térmica | G174: XNT-6800 (384 × 288) | H174: Térmico 384 × 288 | I174: 384 × 288 px | J174: Microbolómetro + CMOS | K174: Óptica fija | L174: Detección térmica 500 m | M174: — | N174: Detección térmica + óptica superpuesta | O174: H.265 (WiseStream II) / H.264 | P174: Perfil S, T, G | Q174: E/S integrada | R174: 1 E / 1 S | S174: microSD 256 GB | T174: IP66 | U174: 802.3at | V174: 25 W máx | W174: -30 °C a +55 °C | X174: Ø 160 × 268 mm | Y174: 3.5 kg | Z174: CE, FCC | AA174: Exterior | AB174: 2450 | AE174: Variante económica de la gama
B175: 171 | C175: Hanwha Vision (Wisenet) | D175: Premium | E175: Corea del Sur | F175: Térmica | G175: XNT-6800 (640 × 480) | H175: Térmico 384 × 288 | I175: 384 × 288 px | J175: Microbolómetro + CMOS | K175: Óptica fija | L175: Detección térmica 500 m | M175: — | N175: Detección térmica + óptica superpuesta | O175: H.265 (WiseStream II) / H.264 | P175: Perfil S, T, G | Q175: E/S integrada | R175: 1 E / 1 S | S175: microSD 256 GB | T175: IP66 | U175: 802.3at | V175: 25 W máx | W175: -30 °C a +55 °C | X175: Ø 160 × 268 mm | Y175: 3.5 kg | Z175: CE, FCC | AA175: Exterior | AB175: 3675 | AE175: Gama de entrada
B176: 172 | C176: Hanwha Vision (Wisenet) | D176: Premium | E176: Corea del Sur | F176: Térmica | G176: TNO-4040TLP | H176: Térmico 640 × 480 | I176: 640 × 480 px | J176: Microbolómetro + CMOS | K176: Óptica fija | L176: Detección térmica 500 m | M176: — | N176: Detección térmica + óptica superpuesta | O176: H.265 (WiseStream II) / H.264 | P176: Perfil S, T, G | Q176: E/S integrada | R176: 1 E / 1 S | S176: microSD 256 GB | T176: IP66 | U176: 802.3at | V176: 25 W máx | W176: -30 °C a +55 °C | X176: Ø 160 × 268 mm | Y176: 3.5 kg | Z176: CE, FCC | AA176: Exterior | AB176: 4900 | AE176: Cámara térmica biespectral
B177: 173 | C177: Hanwha Vision (Wisenet) | D177: Premium | E177: Corea del Sur | F177: Térmica | G177: TNO-7180RLP | H177: Térmico 640 × 480 | I177: 640 × 480 px | J177: Microbolómetro + CMOS | K177: Óptica fija | L177: Detección térmica 500 m | M177: — | N177: Detección térmica + óptica superpuesta | O177: H.265 (WiseStream II) / H.264 | P177: Perfil S, T, G | Q177: E/S integrada | R177: 1 E / 1 S | S177: microSD 256 GB | T177: IP66 | U177: 802.3at | V177: 25 W máx | W177: -30 °C a +55 °C | X177: Ø 160 × 268 mm | Y177: 3.5 kg | Z177: CE, FCC | AA177: Exterior | AB177: 7350 | AE177: Resolución y rendimiento mejorados
B178: 174 | C178: Hanwha Vision (Wisenet) | D178: Premium | E178: Corea del Sur | F178: Térmica | G178: TNO-C80D-TLP | H178: Térmico 640 × 480 | I178: 640 × 480 px | J178: Microbolómetro + CMOS | K178: Óptica fija | L178: Detección térmica 500 m | M178: — | N178: Detección térmica + óptica superpuesta | O178: H.265 (WiseStream II) / H.264 | P178: Perfil S, T, G | Q178: E/S integrada | R178: 1 E / 1 S | S178: microSD 256 GB | T178: IP66 | U178: 802.3at | V178: 25 W máx | W178: -30 °C a +55 °C | X178: Ø 160 × 268 mm | Y178: 3.5 kg | Z178: CE, FCC | AA178: Exterior | AB178: 10780 | AE178: Tope de gama — máxima especificación
B179: 175 | C179: Hanwha Vision (Wisenet) | D179: Premium | E179: Corea del Sur | F179: LPR (Matrículas) | G179: XNO-6083R (ANPR) | H179: 2 MP | I179: 1920 × 1080 | J179: 1/2.7" CMOS | K179: 2.8 mm fijo | L179: IR 30 m — obturador rápido | M179: WDR 120 dB | N179: LPR vía licencia Wisenet WAVE | O179: H.265 (WiseStream II) / H.264 | P179: Perfil S, T, G | Q179: E/S integrada | R179: 1 E / 1 S | S179: microSD 256 GB | T179: IP66 | U179: 802.3af | V179: 9 W máx | W179: -30 °C a +55 °C | X179: 283 × 89 × 88 mm | Y179: 800 g | Z179: CE, FCC | AA179: Exterior | AB179: 190 | AE179: Variante económica de la gama
B180: 176 | C180: Hanwha Vision (Wisenet) | D180: Premium | E180: Corea del Sur | F180: LPR (Matrículas) | G180: XNO-L6083R (ANPR) | H180: 4 MP | I180: 2560 × 1440 | J180: 1/2.7" CMOS | K180: 2.8 mm fijo | L180: IR 30 m — obturador rápido | M180: WDR 120 dB | N180: LPR vía licencia Wisenet WAVE | O180: H.265 (WiseStream II) / H.264 | P180: Perfil S, T, G | Q180: E/S integrada | R180: 1 E / 1 S | S180: microSD 256 GB | T180: IP66 | U180: 802.3af | V180: 9 W máx | W180: -30 °C a +55 °C | X180: 283 × 89 × 88 mm | Y180: 800 g | Z180: CE, FCC | AA180: Exterior | AB180: 285 | AE180: Gama de entrada
B181: 177 | C181: Hanwha Vision (Wisenet) | D181: Premium | E181: Corea del Sur | F181: LPR (Matrículas) | G181: XNO-C6083R (ANPR) | H181: 8 MP (4K) | I181: 3840 × 2160 | J181: 1/2.7" CMOS | K181: 2.8 mm fijo | L181: IR 30 m — obturador rápido | M181: WDR 120 dB | N181: LPR vía licencia Wisenet WAVE | O181: H.265 (WiseStream II) / H.264 | P181: Perfil S, T, G | Q181: E/S integrada | R181: 1 E / 1 S | S181: microSD 256 GB | T181: IP66 | U181: 802.3af | V181: 9 W máx | W181: -30 °C a +55 °C | X181: 283 × 89 × 88 mm | Y181: 800 g | Z181: CE, FCC | AA181: Exterior | AB181: 380 | AE181: Requiere licencia LPR del VMS
B182: 178 | C182: Hanwha Vision (Wisenet) | D182: Premium | E182: Corea del Sur | F182: LPR (Matrículas) | G182: TNO-7180RLP | H182: 8 MP (4K) | I182: 3840 × 2160 | J182: 1/2.7" CMOS | K182: 2.8 mm fijo | L182: IR 30 m — obturador rápido | M182: WDR 120 dB | N182: LPR vía licencia Wisenet WAVE | O182: H.265 (WiseStream II) / H.264 | P182: Perfil S, T, G | Q182: E/S integrada | R182: 1 E / 1 S | S182: microSD 256 GB | T182: IP66 | U182: 802.3af | V182: 9 W máx | W182: -30 °C a +55 °C | X182: 283 × 89 × 88 mm | Y182: 800 g | Z182: CE, FCC | AA182: Exterior | AB182: 570 | AE182: Resolución y rendimiento mejorados
B183: 179 | C183: Hanwha Vision (Wisenet) | D183: Premium | E183: Corea del Sur | F183: LPR (Matrículas) | G183: PNM-C34404RQPZ (ANPR) | H183: 8 MP (4K) | I183: 3840 × 2160 | J183: 1/2.7" CMOS | K183: 2.8 mm fijo | L183: IR 30 m — obturador rápido | M183: WDR 120 dB | N183: LPR vía licencia Wisenet WAVE | O183: H.265 (WiseStream II) / H.264 | P183: Perfil S, T, G | Q183: E/S integrada | R183: 1 E / 1 S | S183: microSD 256 GB | T183: IP66 | U183: 802.3af | V183: 9 W máx | W183: -30 °C a +55 °C | X183: 283 × 89 × 88 mm | Y183: 800 g | Z183: CE, FCC | AA183: Exterior | AB183: 835 | AE183: Tope de gama — máxima especificación
B184: 180 | C184: Hanwha Vision (Wisenet) | D184: Premium | E184: Corea del Sur | F184: Dual-Lente | G184: PNM-9022V | H184: 8 MP (2× 4 MP) | I184: 2× 2560 × 1440 | J184: 2× 1/2.8" CMOS | K184: 2× varifocal | L184: IR 20 m | M184: WDR | N184: Multidireccional 180° | O184: H.265 (WiseStream II) / H.264 | P184: Perfil S, T, G | Q184: E/S integrada | R184: 1 E / 1 S | S184: microSD 256 GB | T184: IK10 / IP66 | U184: 802.3af | V184: 20 W máx | W184: -30 °C a +55 °C | X184: Ø 156 × 92 mm | Y184: 1.1 kg | Z184: CE, FCC | AA184: Interior/Exterior | AB184: 750 | AE184: Variante económica de la gama
B185: 181 | C185: Hanwha Vision (Wisenet) | D185: Premium | E185: Corea del Sur | F185: Dual-Lente | G185: PNM-9320VQP | H185: 16 MP (2× 8 MP) | I185: 2× 3840 × 2160 | J185: 2× 1/2.8" CMOS | K185: 2× varifocal | L185: IR 20 m | M185: WDR | N185: Multidireccional 180° | O185: H.265 (WiseStream II) / H.264 | P185: Perfil S, T, G | Q185: E/S integrada | R185: 1 E / 1 S | S185: microSD 256 GB | T185: IK10 / IP66 | U185: 802.3af | V185: 20 W máx | W185: -30 °C a +55 °C | X185: Ø 156 × 92 mm | Y185: 1.1 kg | Z185: CE, FCC | AA185: Interior/Exterior | AB185: 1125 | AE185: Gama de entrada
... B218: 214 | C218: Avigilon (Motorola) | D218: Premium | E218: Canadá | F218: PTZ | G218: H6A-PTZ-AC | H218: 8 MP (4K) | I218: 3840 × 2160 | J218: 1/2.8" CMOS | K218: 32× zoom óptico | L218: IR 100 m | M218: WDR | N218: Seguimiento automático + analíticas | O218: H.265 (HDSM SmartCodec) / H.264 | P218: Perfil S, T | Q218: E/S integrada | R218: 1 E / 1 S | S218: microSD 256 GB | T218: IP66 / NEMA 4X | U218: 802.3at | V218: 45 W máx | W218: -40 °C a +50 °C | X218: Ø 216 × 375 mm | Y218: 5.0 kg | Z218: UL, CE, FCC | AA218: Exterior | AB218: 9240 | AE218: Tope de gama — máxima especificación
B219: 215 | C219: Avigilon (Motorola) | D219: Premium | E219: Canadá | F219: Mini PTZ | G219: No disponible en portafolio | AE219: Avigilon no ofrece mini PTZ; ver H5A PTZ
B220: 216 | C220: Avigilon (Motorola) | D220: Premium | E220: Canadá | F220: Turrón (Box) | G220: No disponible en portafolio | AE220: Sin cámara box en portafolio (líneas dome/bullet/PTZ/fisheye)
B221: 217 | C221: Avigilon (Motorola) | D221: Premium | E221: Canadá | F221: Ojo de Pez (Fisheye) | G221: H4-FE | H221: 8 MP | I221: 3840 × 2160 (360°) | J221: 1/1.8" CMOS | K221: 1.4 mm fijo — 360° | L221: IR integrada 20 m | M221: WDR | N221: Panorámica dewarped + analíticas | O221: H.265 (HDSM SmartCodec) / H.264 | P221: Perfil S, T | Q221: E/S integrada | R221: 1 E / 1 S | S221: microSD 256 GB | T221: IK10 / IP66 | U221: 802.3af | V221: 10 W máx | W221: -40 °C a +50 °C | X221: Ø 168 × 68 mm | Y221: 900 g | Z221: UL, CE, FCC | AA221: Interior/Exterior | AB221: 475 | AE221: Variante económica de la gama
B222: 218 | C222: Avigilon (Motorola) | D222: Premium | E222: Canadá | F222: Ojo de Pez (Fisheye) | G222: H5A-FE | H222: 8 MP | I222: 3840 × 2160 (360°) | J222: 1/1.8" CMOS | K222: 1.4 mm fijo — 360° | L222: IR integrada 20 m | M222: WDR | N222: Panorámica dewarped + analíticas | O222: H.265 (HDSM SmartCodec) / H.264 | P222: Perfil S, T | Q222: E/S integrada | R222: 1 E / 1 S | S222: microSD 256 GB | T222: IK10 / IP66 | U222: 802.3af | V222: 10 W máx | W222: -40 °C a +50 °C | X222: Ø 168 × 68 mm | Y222: 900 g | Z222: UL, CE, FCC | AA222: Interior/Exterior | AB222: 710 | AE222: Gama de entrada
B223: 219 | C223: Avigilon (Motorola) | D223: Premium | E223: Canadá | F223: Ojo de Pez (Fisheye) | G223: H5A-FEB | H223: 12 MP | I223: 4000 × 3000 (360°) | J223: 1/1.8" CMOS | K223: 1.4 mm fijo — 360° | L223: IR integrada 20 m | M223: WDR | N223: Panorámica dewarped + analíticas | O223: H.265 (HDSM SmartCodec) / H.264 | P223: Perfil S, T | Q223: E/S integrada | R223: 1 E / 1 S | S223: microSD 256 GB | T223: IK10 / IP66 | U223: 802.3af | V223: 10 W máx | W223: -40 °C a +50 °C | X223: Ø 168 × 68 mm | Y223: 900 g | Z223: UL, CE, FCC | AA223: Interior/Exterior | AB223: 950 | AE223: Fisheye 360°
B224: 220 | C224: Avigilon (Motorola) | D224: Premium | E224: Canadá | F224: Ojo de Pez (Fisheye) | G224: H6A-FE | H224: 12 MP | I224: 4000 × 3000 (360°) | J224: 1/1.8" CMOS | K224: 1.4 mm fijo — 360° | L224: IR integrada 20 m | M224: WDR | N224: Panorámica dewarped + analíticas | O224: H.265 (HDSM SmartCodec) / H.264 | P224: Perfil S, T | Q224: E/S integrada | R224: 1 E / 1 S | S224: microSD 256 GB | T224: IK10 / IP66 | U224: 802.3af | V224: 10 W máx | W224: -40 °C a +50 °C | X224: Ø 168 × 68 mm | Y224: 900 g | Z224: UL, CE, FCC | AA224: Interior/Exterior | AB224: 1425 | AE224: Resolución y rendimiento mejorados
B225: 221 | C225: Avigilon (Motorola) | D225: Premium | E225: Canadá | F225: Ojo de Pez (Fisheye) | G225: H6A-FEB | H225: 12 MP | I225: 4000 × 3000 (360°) | J225: 1/1.8" CMOS | K225: 1.4 mm fijo — 360° | L225: IR integrada 20 m | M225: WDR | N225: Panorámica dewarped + analíticas | O225: H.265 (HDSM SmartCodec) / H.264 | P225: Perfil S, T | Q225: E/S integrada | R225: 1 E / 1 S | S225: microSD 256 GB | T225: IK10 / IP66 | U225: 802.3af | V225: 10 W máx | W225: -40 °C a +50 °C | X225: Ø 168 × 68 mm | Y225: 900 g | Z225: UL, CE, FCC | AA225: Interior/Exterior | AB225: 2090 | AE225: Tope de gama — máxima especificación
B226: 222 | C226: Avigilon (Motorola) | D226: Premium | E226: Canadá | F226: Multisensor / Panorámica | G226: H4-M2 | H226: 12 MP (4× 3 MP) | I226: 4× 2304 × 1296 | J226: 4× 1/2.8" CMOS | K226: 4× lentes integradas | L226: IR 30 m | M226: WDR | N226: Multidireccional 180° + analíticas | O226: H.265 (HDSM SmartCodec) / H.264 | P226: Perfil S, T | Q226: E/S integrada | R226: 1 E / 1 S | S226: microSD 256 GB | T226: IP66 | U226: 802.3at | V226: 30 W máx | W226: -40 °C a +50 °C | X226: 220 × 220 × 95 mm | Y226: 2.4 kg | Z226: UL, CE, FCC | AA226: Interior/Exterior | AB226: 1400 | AE226: Variante económica de la gama
B227: 223 | C227: Avigilon (Motorola) | D227: Premium | E227: Canadá | F227: Multisensor / Panorámica | G227: H5A-M1 | H227: 20 MP (4× 5 MP) | I227: 4× 2592 × 1944 | J227: 4× 1/2.8" CMOS | K227: 4× lentes integradas | L227: IR 30 m | M227: WDR | N227: Multidireccional 180° + analíticas | O227: H.265 (HDSM SmartCodec) / H.264 | P227: Perfil S, T | Q227: E/S integrada | R227: 1 E / 1 S | S227: microSD 256 GB | T227: IP66 | U227: 802.3at | V227: 30 W máx | W227: -40 °C a +50 °C | X227: 220 × 220 × 95 mm | Y227: 2.4 kg | Z227: UL, CE, FCC | AA227: Interior/Exterior | AB227: 2100 | AE227: Gama de entrada
B228: 224 | C228: Avigilon (Motorola) | D228: Premium | E228: Canadá | F228: Multisensor / Panorámica | G228: H5A-M2 | H228: 32 MP (4× 8 MP) | I228: 4× 3840 × 2160 | J228: 4× 1/2.8" CMOS | K228: 4× lentes integradas | L228: IR 30 m | M228: WDR | N228: Multidireccional 180° + analíticas | O228: H.265 (HDSM SmartCodec) / H.264 | P228: Perfil S, T | Q228: E/S integrada | R228: 1 E / 1 S | S228: microSD 256 GB | T228: IP66 | U228: 802.3at | V228: 30 W máx | W228: -40 °C a +50 °C | X228: 220 × 220 × 95 mm | Y228: 2.4 kg | Z228: UL, CE, FCC | AA228: Interior/Exterior | AB228: 2800 | AE228: 4 sensores independientes
B229: 225 | C229: Avigilon (Motorola) | D229: Premium | E229: Canadá | F229: Multisensor / Panorámica | G229: H5A-M3 | H229: 32 MP (4× 8 MP) | I229: 4× 3840 × 2160 | J229: 4× 1/2.8" CMOS | K229: 4× lentes integradas | L229: IR 30 m | M229: WDR | N229: Multidireccional 180° + analíticas | O229: H.265 (HDSM SmartCodec) / H.264 | P229: Perfil S, T | Q229: E/S integrada | R229: 1 E / 1 S | S229: microSD 256 GB | T229: IP66 | U229: 802.3at | V229: 30 W máx | W229: -40 °C a +50 °C | X229: 220 × 220 × 95 mm | Y229: 2.4 kg | Z229: UL, CE, FCC | AA229: Interior/Exterior | AB229: 4200 | AE229: Resolución y rendimiento mejorados
B230: 226 | C230: Avigilon (Motorola) | D230: Premium | E230: Canadá | F230: Multisensor / Panorámica | G230: H6A-M4 | H230: 48 MP (4× 12 MP) | I230: 4× 4000 × 3000 | J230: 4× 1/2.8" CMOS | K230: 4× lentes integradas | L230: IR 30 m | M230: WDR | N230: Multidireccional 180° + analíticas | O230: H.265 (HDSM SmartCodec) / H.264 | P230: Perfil S, T | Q230: E/S integrada | R230: 1 E / 1 S | S230: microSD 256 GB | T230: IP66 | U230: 802.3at | V230: 30 W máx | W230: -40 °C a +50 °C | X230: 220 × 220 × 95 mm | Y230: 2.4 kg | Z230: UL, CE, FCC | AA230: Interior/Exterior | AB230: 6160 | AE230: Tope de gama — máxima especificación
B231: 227 | C231: Avigilon (Motorola) | D231: Premium | E231: Canadá | F231: Oculta (Pinhole) | G231: No disponible en portafolio | AE231: Avigilon no fabrica cámaras ocultas
B232: 228 | C232: Avigilon (Motorola) | D232: Premium | E232: Canadá | F232: Térmica | G232: H4-THR | H232: Térmico 384 × 288 | I232: 384 × 288 px | J232: Microbolómetro + CMOS 4K | K232: Óptica fija | L232: Detección térmica 700 m | M232: — | N232: Detección perimetral térmica + óptica superpuesta | O232: H.265 (HDSM SmartCodec) / H.264 | P232: Perfil S, T | Q232: E/S integrada | R232: 1 E / 1 S | S232: microSD 256 GB | T232: IP66 | U232: 802.3at | V232: 25 W máx | W232: -40 °C a +50 °C | X232: Ø 150 × 300 mm | Y232: 3.0 kg | Z232: UL, CE, FCC | AA232: Exterior | AB232: 3250 | AE232: Variante económica de la gama
B233: 229 | C233: Avigilon (Motorola) | D233: Premium | E233: Canadá | F233: Térmica | G233: H5A-THR-DZ1 | H233: Térmico 384 × 288 | I233: 384 × 288 px | J233: Microbolómetro + CMOS 4K | K233: Óptica fija | L233: Detección térmica 700 m | M233: — | N233: Detección perimetral térmica + óptica superpuesta | O233: H.265 (HDSM SmartCodec) / H.264 | P233: Perfil S, T | Q233: E/S integrada | R233: 1 E / 1 S | S233: microSD 256 GB | T233: IP66 | U233: 802.3at | V233: 25 W máx | W233: -40 °C a +50 °C | X233: Ø 150 × 300 mm | Y233: 3.0 kg | Z233: UL, CE, FCC | AA233: Exterior | AB233: 4875 | AE233: Gama de entrada
B234: 230 | C234: Avigilon (Motorola) | D234: Premium | E234: Canadá | F234: Térmica | G234: H5A-THR-B1 | H234: Térmico 640 × 480 | I234: 640 × 480 px | J234: Microbolómetro + CMOS 4K | K234: Óptica fija | L234: Detección térmica 700 m | M234: — | N234: Detección perimetral térmica + óptica superpuesta | O234: H.265 (HDSM SmartCodec) / H.264 | P234: Perfil S, T | Q234: E/S integrada | R234: 1 E / 1 S | S234: microSD 256 GB | T234: IP66 | U234: 802.3at | V234: 25 W máx | W234: -40 °C a +50 °C | X234: Ø 150 × 300 mm | Y234: 3.0 kg | Z234: UL, CE, FCC | AA234: Exterior | AB234: 6500 | AE234: Térmica y óptica en un cuerpo
B235: 231 | C235: Avigilon (Motorola) | D235: Premium | E235: Canadá | F235: Térmica | G235: H6A-THR-DZ1 | H235: Térmico 640 × 480 | I235: 640 × 480 px | J235: Microbolómetro + CMOS 4K | K235: Óptica fija | L235: Detección térmica 700 m | M235: — | N235: Detección perimetral térmica + óptica superpuesta | O235: H.265 (HDSM SmartCodec) / H.264 | P235: Perfil S, T | Q235: E/S integrada | R235: 1 E / 1 S | S235: microSD 256 GB | T235: IP66 | U235: 802.3at | V235: 25 W máx | W235: -40 °C a +50 °C | X235: Ø 150 × 300 mm | Y235: 3.0 kg | Z235: UL, CE, FCC | AA235: Exterior | AB235: 9750 | AE235: Resolución y rendimiento mejorados
B236: 232 | C236: Avigilon (Motorola) | D236: Premium | E236: Canadá | F236: Térmica | G236: H6A-THR-B2 | H236: Térmico 640 × 480 | I236: 640 × 480 px | J236: Microbolómetro + CMOS 4K | K236: Óptica fija | L236: Detección térmica 700 m | M236: — | N236: Detección perimetral térmica + óptica superpuesta | O236: H.265 (HDSM SmartCodec) / H.264 | P236: Perfil S, T | Q236: E/S integrada | R236: 1 E / 1 S | S236: microSD 256 GB | T236: IP66 | U236: 802.3at | V236: 25 W máx | W236: -40 °C a +50 °C | X236: Ø 150 × 300 mm | Y236: 3.0 kg | Z236: UL, CE, FCC | AA236: Exterior | AB236: 14300 | AE236: Tope de gama — máxima especificación
B237: 233 | C237: Avigilon (Motorola) | D237: Premium | E237: Canadá | F237: LPR (Matrículas) | G237: H4-LPR | H237: 2 MP | I237: 1920 × 1080 | J237: 1/2.8" CMOS | K237: Optimizada captura de matrículas | L237: IR 30 m — obturador rápido | M237: WDR | N237: ALPR integrado con Avigilon AI Center | O237: H.265 (HDSM SmartCodec) / H.264 | P237: Perfil S, T | Q237: E/S integrada | R237: 1 E / 1 S | S237: microSD 256 GB | T237: IP66 | U237: 802.3af | V237: 12 W máx | W237: -40 °C a +50 °C | X237: 82 × 89 × 244 mm | Y237: 1.3 kg | Z237: UL, CE, FCC | AA237: Exterior | AB237: 750 | AE237: Variante económica de la gama
B238: 234 | C238: Avigilon (Motorola) | D238: Premium | E238: Canadá | F238: LPR (Matrículas) | G238: H5A-LPR-1 | H238: 4 MP | I238: 2560 × 1440 | J238: 1/2.8" CMOS | K238: Optimizada captura de matrículas | L238: IR 30 m — obturador rápido | M238: WDR | N238: ALPR integrado con Avigilon AI Center | O238: H.265 (HDSM SmartCodec) / H.264 | P238: Perfil S, T | Q238: E/S integrada | R238: 1 E / 1 S | S238: microSD 256 GB | T238: IP66 | U238: 802.3af | V238: 12 W máx | W238: -40 °C a +50 °C | X238: 82 × 89 × 244 mm | Y238: 1.3 kg | Z238: UL, CE, FCC | AA238: Exterior | AB238: 1125 | AE238: Gama de entrada
B239: 235 | C239: Avigilon (Motorola) | D239: Premium | E239: Canadá | F239: LPR (Matrículas) | G239: H5A-LPR-2 | H239: 8 MP (4K) | I239: 3840 × 2160 | J239: 1/2.8" CMOS | K239: Optimizada captura de matrículas | L239: IR 30 m — obturador rápido | M239: WDR | N239: ALPR integrado con Avigilon AI Center | O239: H.265 (HDSM SmartCodec) / H.264 | P239: Perfil S, T | Q239: E/S integrada | R239: 1 E / 1 S | S239: microSD 256 GB | T239: IP66 | U239: 802.3af | V239: 12 W máx | W239: -40 °C a +50 °C | X239: 82 × 89 × 244 mm | Y239: 1.3 kg | Z239: UL, CE, FCC | AA239: Exterior | AB239: 1500 | AE239: Requiere licencia AI Center
B240: 236 | C240: Avigilon (Motorola) | D240: Premium | E240: Canadá | F240: LPR (Matrículas) | G240: H5A-LPR-3 | H240: 8 MP (4K) | I240: 3840 × 2160 | J240: 1/2.8" CMOS | K240: Optimizada captura de matrículas | L240: IR 30 m — obturador rápido | M240: WDR | N240: ALPR integrado con Avigilon AI Center | O240: H.265 (HDSM SmartCodec) / H.264 | P240: Perfil S, T | Q240: E/S integrada | R240: 1 E / 1 S | S240: microSD 256 GB | T240: IP66 | U240: 802.3af | V240: 12 W máx | W240: -40 °C a +50 °C | X240: 82 × 89 × 244 mm | Y240: 1.3 kg | Z240: UL, CE, FCC | AA240: Exterior | AB240: 2250 | AE240: Resolución y rendimiento mejorados
B241: 237 | C241: Avigilon (Motorola) | D241: Premium | E241: Canadá | F241: LPR (Matrículas) | G241: H6A-LPR-4 | H241: 8 MP (4K) | I241: 3840 × 2160 | J241: 1/2.8" CMOS | K241: Optimizada captura de matrículas | L241: IR 30 m — obturador rápido | M241: WDR | N241: ALPR integrado con Avigilon AI Center | O241: H.265 (HDSM SmartCodec) / H.264 | P241: Perfil S, T | Q241: E/S integrada | R241: 1 E / 1 S | S241: microSD 256 GB | T241: IP66 | U241: 802.3af | V241: 12 W máx | W241: -40 °C a +50 °C | X241: 82 × 89 × 244 mm | Y241: 1.3 kg | Z241: UL, CE, FCC | AA241: Exterior | AB241: 3300 | AE241: Tope de gama — máxima especificación
B242: 238 | C242: Avigilon (Motorola) | D242: Premium | E242: Canadá | F242: Dual-Lente | G242: No disponible en portafolio | AE242: Sin dual-lente; referencia multidireccional: H5A Multisensor
B243: 239 | C243: Avigilon (Motorola) | D243: Premium | E243: Canadá | F243: IA Integrada | G243: H5A-DZ | H243: 2 MP | I243: 1920 × 1080 | J243: 1/2.8" CMOS | K243: 3–9 mm varifocal | L243: IR 30 m | M243: WDR | N243: Appearance Search + reconocimiento facial (IA) | O243: H.265 (HDSM SmartCodec) / H.264 | P243: Perfil S, T | Q243: E/S integrada | R243: 1 E / 1 S | S243: microSD 256 GB | T243: IK10 | U243: 802.3af | V243: 12 W máx | W243: -40 °C a +50 °C | X243: Ø 158 × 110 mm | Y243: 1.1 kg | Z243: UL, CE, FCC | AA243: Interior/Exterior | AB243: 445 | AE243: Variante económica de la gama
B244: 240 | C244: Avigilon (Motorola) | D244: Premium | E244: Canadá | F244: IA Integrada | G244: H6A-DP1 | H244: 4 MP | I244: 2560 × 1440 | J244: 1/2.8" CMOS | K244: 3–9 mm varifocal | L244: IR 30 m | M244: WDR | N244: Appearance Search + reconocimiento facial (IA) | O244: H.265 (HDSM SmartCodec) / H.264 | P244: Perfil S, T | Q244: E/S integrada | R244: 1 E / 1 S | S244: microSD 256 GB | T244: IK10 | U244: 802.3af | V244: 12 W máx | W244: -40 °C a +50 °C | X244: Ø 158 × 110 mm | Y244: 1.1 kg | Z244: UL, CE, FCC | AA244: Interior/Exterior | AB244: 670 | AE244: Gama de entrada
B245: 241 | C245: Avigilon (Motorola) | D245: Premium | E245: Canadá | F245: IA Integrada | G245: H6A-B2 | H245: 4 MP | I245: 2560 × 1440 | J245: 1/2.8" CMOS | K245: 3–9 mm varifocal | L245: IR 30 m | M245: WDR | N245: Appearance Search + reconocimiento facial (IA) | O245: H.265 (HDSM SmartCodec) / H.264 | P245: Perfil S, T | Q245: E/S integrada | R245: 1 E / 1 S | S245: microSD 256 GB | T245: IK10 | U245: 802.3af | V245: 12 W máx | W245: -40 °C a +50 °C | X245: Ø 158 × 110 mm | Y245: 1.1 kg | Z245: UL, CE, FCC | AA245: Interior/Exterior | AB245: 890 | AE245: Gama H6A con IA avanzada
B246: 242 | C246: Avigilon (Motorola) | D246: Premium | E246: Canadá | F246: IA Integrada | G246: H6X-D1 | H246: 8 MP (4K) | I246: 3840 × 2160 | J246: 1/2.8" CMOS | K246: 3–9 mm varifocal | L246: IR 30 m | M246: WDR | N246: Appearance Search + reconocimiento facial (IA) | O246: H.265 (HDSM SmartCodec) / H.264 | P246: Perfil S, T | Q246: E/S integrada | R246: 1 E / 1 S | S246: microSD 256 GB | T246: IK10 | U246: 802.3af | V246: 12 W máx | W246: -40 °C a +50 °C | X246: Ø 158 × 110 mm | Y246: 1.1 kg | Z246: UL, CE, FCC | AA246: Interior/Exterior | AB246: 1335 | AE246: Resolución y rendimiento mejorados
B247: 243 | C247: Avigilon (Motorola) | D247: Premium | E247: Canadá | F247: IA Integrada | G247: H6X-B2 | H247: 8 MP (4K) | I247: 3840 × 2160 | J247: 1/2.8" CMOS | K247: 3–9 mm varifocal | L247: IR 30 m | M247: WDR | N247: Appearance Search + reconocimiento facial (IA) | O247: H.265 (HDSM SmartCodec) / H.264 | P247: Perfil S, T | Q247: E/S integrada | R247: 1 E / 1 S | S247: microSD 256 GB | T247: IK10 | U247: 802.3af | V247: 12 W máx | W247: -40 °C a +50 °C | X247: Ø 158 × 110 mm | Y247: 1.1 kg | Z247: UL, CE, FCC | AA247: Interior/Exterior | AB247: 1960 | AE247: Tope de gama — máxima especificación
B248: 244 | C248: Avigilon (Motorola) | D248: Premium | E248: Canadá | F248: Interior WiFi | G248: No disponible en portafolio | AE248: Portafolio 100% PoE administrado en Avigilon Cloud / ACC
B249: 245 | C249: Pelco (Motorola) | D249: Premium | E249: EE. UU. | F249: Domo | G249: IME219-1IS | H249: 2 MP | I249: 1920 × 1080 | J249: 1/2.7" CMOS | K249: 3–9 mm varifocal | L249: Día/Noche — IR 30 m | M249: WDR | N249: Analíticas Sarix | O249: H.265 / H.264 (Smart Compression) | P249: Perfil S, T, G | Q249: E/S integrada | R249: 1 E / 1 S | S249: microSD 256 GB | T249: IK10 | U249: 802.3af | V249: 12 W máx | W249: -30 °C a +60 °C | X249: Ø 148 × 100 mm | Y249: 800 g | Z249: UL, CE, FCC, NEMA 4X | AA249: Interior/Exterior | AB249: 345 | AE249: Variante económica de la gama
B250: 246 | C250: Pelco (Motorola) | D250: Premium | E250: EE. UU. | F250: Domo | G250: IME319-1IS | H250: 4 MP | I250: 2560 × 1440 | J250: 1/2.7" CMOS | K250: 3–9 mm varifocal | L250: Día/Noche — IR 30 m | M250: WDR | N250: Analíticas Sarix | O250: H.265 / H.264 (Smart Compression) | P250: Perfil S, T, G | Q250: E/S integrada | R250: 1 E / 1 S | S250: microSD 256 GB | T250: IK10 | U250: 802.3af | V250: 12 W máx | W250: -30 °C a +60 °C | X250: Ø 148 × 100 mm | Y250: 800 g | Z250: UL, CE, FCC, NEMA 4X | AA250: Interior/Exterior | AB250: 520 | AE250: Gama de entrada
...

Sheet Equipamiento
B2: Base de Datos de Equipamiento — NVR · Almacenamiento · Switch PoE · UPS · Monitor · Rack · Cableado · Accesorios · Fuentes · VMS
B4: N° | C4: Categoría | D4: Marca | E4: Nivel | F4: Modelo | G4: Descripción | H4: Especificación Principal | I4: Características | J4: Compatibilidad / Integración | K4: Alimentación | L4: Montaje / Formato | M4: Dimensiones | N4: Peso | O4: Precio Ref. (USD) | P4: Proveedor | Q4: Stock | R4: Observaciones
B5: 1 | C5: NVR / DVR | D5: Axis Communications | E5: Premium | F5: AXIS S3008 Recorder | G5: NVR IP llave en mano para cámaras Axis y ONVIF | H5: 8 canales · HDD 2 TB incluido | I5: Sin configuración previa, H.265, HTTPS, actualizaciones automáticas | J5: Cámaras Axis + ONVIF S/T | K5: 100–240 VAC | L5: Escritorio / rack 1U | M5: 445 × 380 × 45 mm | N5: 4.1 kg | O5: 449 | R5: La opción más simple para proyectos pequeños Axis
B6: 2 | C6: NVR / DVR | D6: Hikvision | E6: Medio | F6: DS-7608NXI-K2/8P | G6: NVR AcuSense con PoE integrado | H6: 8 canales · 8 Puertos PoE · 2 bahías SATA | I6: H.265+, decodificación 8 MP, análisis AcuSearch (rostro/vehículo), HDMI 4K + VGA | J6: ONVIF (Perfil S) — cámaras de cualquier marca | K6: 100–240 VAC | L6: Rack 1U / escritorio | M6: 445 × 390 × 75 mm | N6: 4.0 kg | O6: 289 | R6: Estándar de la industria para instalaciones de 4–8 cámaras
B7: 3 | C7: NVR / DVR | D7: Hikvision | E7: Medio | F7: DS-7208HUHI-K2 | G7: DVR híbrido Turbo HD 5.0 | H7: 8 canales coaxiales + 4 IP · 2 bahías SATA | I7: HDTVI hasta 8 MP, audio sobre coaxial, compatible TVI/AHD/CVI/CVBS | J7: Cámaras analógicas HD + hasta 4 IP ONVIF | K7: 100–240 VAC | L7: Rack 1U / escritorio | M7: 380 × 320 × 48 mm | N7: 2.5 kg | O7: 139 | R7: Para modernizar sistemas coaxiales existentes
B8: 4 | C8: NVR / DVR | D8: Dahua Technology | E8: Medio | F8: NVR5216-16P-4KS2E | G8: NVR WizSense con PoE | H8: 16 canales · 16 PoE · 2 bahías SATA | I8: H.265+, SMD (detección inteligente de movimiento), ANPR opcional, HDMI+VGA | J8: ONVIF (Perfil S/T) | K8: 100–240 VAC | L8: Rack 1U / escritorio | M8: 440 × 410 × 75 mm | N8: 4.5 kg | O8: 519 | R8: Buena relación canales/PoE para proyectos medianos
B9: 5 | C9: NVR / DVR | D9: Uniview (UNV) | E9: Medio | F9: NVR302-16S-P16 | G9: NVR profesional con PoE | H9: 16 canales · 16 PoE · 2 bahías SATA | I9: H.265, Lighthouse (búsqueda por IA), almacenamiento en nube EZStation | J9: ONVIF (Perfil S/T/G) | K9: 100–240 VAC | L9: Rack 1U / escritorio | M9: 440 × 393 × 68 mm | N9: 4.2 kg | O9: 379 | R9: Interfaz EZStation/EZView muy valorada por integradores
B10: 6 | C10: NVR / DVR | D10: Hanwha Vision (Wisenet) | E10: Premium | F10: HRX-810-4TB | G10: DVR pentabrid con HDD preinstalado | H10: 8 canales analógicos + IP · 4 TB incluidos | I10: Soporta AHD/TVI/CVI/CVBS + IP, WiseStream, búsqueda inteligente | J10: Analógicos HD + IP ONVIF | K10: 100–240 VAC | L10: Escritorio / rack 1U | M10: 430 × 380 × 88 mm | N10: 3.8 kg | O10: 439 | R10: Incluye disco de 4 TB listo para grabar
B11: 7 | C11: NVR / DVR | D11: Reolink | E11: Económico | F11: RLN16-410 | G11: NVR PoE para cámaras Reolink/ONVIF | H11: 16 canales · 4 bahías SATA (sin HDD) | I11: H.264/H.265, acceso remoto Reolink App, sin análisis IA en el NVR | J11: Cámaras Reolink + RTSP/ONVIF limitado | K11: 100–240 VAC | L11: Escritorio / rack 1U | M11: 440 × 410 × 65 mm | N11: 3.6 kg | O11: 269 | R11: Comprar HDD aparte (ver categoría Almacenamiento)
B12: 8 | C12: NVR / DVR | D12: TP-Link VIGI | E12: Económico | F12: VIGI NVR1008H-8P | G12: NVR VIGI con PoE extendido | H12: 8 canales · 8 PoE · 1 bahía SATA | I12: H.265+, PoE hasta 250 m en modo extendido, VIGI Security Manager | J12: Cámaras VIGI + ONVIF | K12: 100–240 VAC | L12: Escritorio / rack 1U | M12: 315 × 240 × 45 mm | N12: 1.9 kg | O12: 159 | R12: Ideal para paquetes VIGI llave en mano
B13: 9 | C13: NVR / DVR | D13: HiLook (Hikvision) | E13: Económico | F13: NVR-208MH-C/8P | G13: NVR HiLook con PoE | H13: 8 canales · 8 PoE · 2 bahías SATA | I13: H.265+, AcuSearch simplificado, HDMI 4K | J13: ONVIF (Perfil S) — línea económica de Hikvision | K13: 100–240 VAC | L13: Rack 1U / escritorio | M13: 385 × 315 × 52 mm | N13: 3.0 kg | O13: 139 | R13: Equivalente económico del DS-7608NXI
B14: 10 | C14: NVR / DVR | D14: Imou (Dahua) | E14: Económico | F14: NVR1008H-08P | G14: NVR compacto Imou con PoE | H14: 8 canales · 8 PoE · 1 bahía SATA | I14: H.265+, app Imou Life, unidad SSD 2.5" soportada | J14: Cámaras Imou + ONVIF | K14: 100–240 VAC | L14: Escritorio | M14: 300 × 225 × 45 mm | N14: 1.6 kg | O14: 119 | R14: Para hogares y pequeñas oficinas con cámaras Imou
B15: 11 | C15: Almacenamiento (HDD) | D15: Seagate | E15: Medio | F15: SkyHawk AI 8 TB (ST8000VE001) | G15: Disco de vigilancia con soporte IA | H15: 8 TB · 550 TB/año de carga de trabajo | I15: ImagePerfect AI, hasta 32 flujos de IA, MTBF 1M h, RV (antivibración) | J15: NVR/DVR SATA III | K15: SATA 6 Gb/s | L15: Interno 3.5" | M15: 147 × 101.85 × 26.1 mm | N15: 680 g | O15: 189 | R15: Recomendado cuando el NVR ejecuta analíticas de IA
B16: 12 | C16: Almacenamiento (HDD) | D16: Western Digital | E16: Medio | F16: Purple Pro 8 TB (WD82PURP) | G16: Disco de vigilancia gama profesional | H16: 8 TB · 550 TB/año | I16: AllFrame AI (reduce pérdida de fotogramas), hasta 32 flujos IA, MTBF 1M h | J16: NVR/DVR SATA III | K16: SATA 6 Gb/s | L16: Interno 3.5" | M16: 147 × 101.6 × 26.1 mm | N16: 650 g | O16: 185 | R16: Alternativa directa al SkyHawk AI
... B66: 62 | C66: Software VMS | D66: Perspective Software | E66: Económico | F66: Blue Iris v5 (licencia) | G66: VMS ligero para Windows | H66: Hasta 64 cámaras · 1 licencia completa | I66: Grabación por movimiento/IA (CodeProject), app móvil, bajo costo de hardware | J66: Cámaras RTSP/ONVIF de cualquier marca | K66: PC Windows | L66: Licencia electrónica | M66: — | N66: — | O66: 70 | R66: Favorita DIY; requiere PC dedicado potente

Sheet Comparativa
B2: Comparativa por Tipo de Cámara — Modelos de Referencia
B5: 1. Domo
B6: Cámara compacta de techo o pared, discreta, para interiores y exteriores
B7: Especificación | C7: Axis Communications AXIS P3245-LVE | D7: Hikvision DS-2CD2131G0-I | E7: HiLook (Hikvision) IPC-D150H-MU
B8: Nivel | C8: Premium | D8: Medio | E8: Económico
B9: Resolución | C9: 4 MP | D9: 4 MP | E9: 4 MP
B10: Resolución Máx. | C10: 2560 × 1440 | D10: 2560 × 1440 | E10: 2560 × 1440
B11: Sensor | C11: 1/2.8" Sony Starvis | D11: 1/2.8" CMOS | E11: 1/2.7" CMOS
B12: Lente | C12: 3–9 mm varifocal P-Iris | D12: 2.8 mm fijo (4 mm opcional) | E12: 3.6 mm fijo
B13: Visión Nocturna | C13: OptimizedIR 40 m | D13: IR 30 m | E13: IR 30 m
B14: WDR | C14: Forensic WDR | D14: WDR 120 dB | E14: WDR 120 dB
B15: Analíticas IA | C15: AXIS Object Analytics | D15: EasyIP 4.0 — analíticas básicas | E15: Analíticas básicas (movimiento, cruce de línea)
B16: Audio | C16: E/S (según modelo) | D16: 1 E / 1 S (según modelo) | E16: Micrófono integrado (según modelo)
B17: Protección | C17: IP66 / IK10 | D17: IP66 | E17: IP66
B18: PoE | C18: 802.3af | D18: 802.3af | E18: 802.3af
... B20: Temp. Operación | C20: -30 °C a +50 °C | D20: -30 °C a +60 °C | E20: -30 °C a +60 °C
B21: Precio Ref. (USD) | C21: 1090 | D21: 95 | E21: 50
B23: 2. Domo Antivandálica
B24: Domo reforzado IK10 para ambientes con alto riesgo de vandalismo
B25: Especificación | C25: Bosch Security Systems FLEXIDOME IP outdoor 5000i (NDE-5502-AL) | D25: Dahua Technology DH-IPC-HDBW2431T1-AS-S2 | E25: TP-Link VIGI VIGI C450V
B26: Nivel | C26: Premium | D26: Medio | E26: Económico
B27: Resolución | C27: 4 MP | D27: 4 MP | E27: 4 MP
B28: Resolución Máx. | C28: 2560 × 1440 | D28: 2560 × 1440 | E28: 2560 × 1440
B29: Sensor | C29: 1/2.8" CMOS | D29: 1/2.8" CMOS | E29: 1/3" CMOS
B30: Lente | C30: 2.8–10 mm varifocal | D30: 2.7–13.5 mm varifocal | E30: 2.8–8 mm motorizada
B31: Visión Nocturna | C31: IR 30 m | D31: IR 50 m | E31: Full color — LED blanco 30 m
B32: WDR | C32: WDR 120 dB | D32: WDR 120 dB | E32: WDR
B33: Analíticas IA | C33: Analíticas Bosch (movimiento inteligente) | D33: IVS + analíticas | E33: Detección IA personas/vehículos
B34: Audio | C34: E/S integrada | D34: 1 E / 1 S (según modelo) | E34: Micrófono/altavoz integrado
B35: Protección | C35: IP66 / IK10 | D35: IK10 / IP67 | E35: IP66 / IK10
B36: PoE | C36: 802.3af | D36: 802.3af | E36: 802.3af
... B38: Temp. Operación | C38: -30 °C a +55 °C | D38: -30 °C a +60 °C | E38: -20 °C a +50 °C
B39: Precio Ref. (USD) | C39: 890 | D39: 145 | E39: 85
B41: 3. Bala
B42: Formato cilíndrico con soporte; mayor alcance IR, ideal para perímetros
B43: Especificación | C43: Axis Communications AXIS P1467-LE | D43: Hikvision DS-2CD2043G0-I | E43: Reolink RLC-820A
B44: Nivel | C44: Premium | D44: Medio | E44: Económico
B45: Resolución | C45: 4 MP | D45: 4 MP | E45: 4 MP
B46: Resolución Máx. | C46: 2560 × 1440 | D46: 2560 × 1440 | E46: 2560 × 1440
B47: Sensor | C47: 1/2.8" Sony Starvis | D47: 1/1.8" CMOS ColorVu | E47: 1/2.8" CMOS
B48: Lente | C48: 3–9 mm varifocal | D48: 2.8 mm fijo | E48: 4 mm fijo
B49: Visión Nocturna | C49: OptimizedIR 50 m | D49: Full color 24/7 — LED blanco 30 m | E49: IR 30 m
B50: WDR | C50: Forensic WDR | D50: WDR 120 dB | E50: WDR
B51: Analíticas IA | C51: AXIS Object Analytics | D51: AcuSense (personas/vehículos) | E51: Detección IA personas/vehículos
B52: Audio | C52: E/S (según modelo) | D52: 1 E / 1 S (según modelo) | E52: Micrófono integrado
B53: Protección | C53: IP66 / IK09 | D53: IP67 | E53: IP66
B54: PoE | C54: 802.3af | D54: 802.3af | E54: 802.3af
... B56: Temp. Operación | C56: -30 °C a +50 °C | D56: -30 °C a +60 °C | E56: -20 °C a +55 °C
B57: Precio Ref. (USD) | C57: 940 | D57: 130 | E57: 70
B59: 4. PTZ
B60: Pan/Tilt/Zoom motorizado con seguimiento automático para vigilancia activa
B61: Especificación | C61: Axis Communications AXIS P5655-E | D61: Hanwha Vision (Wisenet) XNP-C6403RW | E61: TP-Link VIGI VIGI C320
B62: Nivel | C62: Premium | D62: Premium | E62: Económico
B63: Resolución | C63: 4 MP | D63: 4 MP | E63: 4 MP
B64: Resolución Máx. | C64: 2560 × 1440 | D64: 2560 × 1440 | E64: 2560 × 1440
B65: Sensor | C65: 1/2.8" Sony Starvis | D65: 1/2.8" CMOS | E65: 1/2.8" CMOS
B66: Lente | C66: 32× zoom óptico (4.3–138 mm) | D66: 32× zoom óptico | E66: 22× zoom óptico
B67: Visión Nocturna | C67: OptimizedIR 150 m | D67: IR 50 m + LED blanco | E67: IR 100 m
B68: WDR | C68: Forensic WDR | D68: WDR | E68: WDR
B69: Analíticas IA | C69: Autotracking 2, guarda activa | D69: WiseAI II — autotracking IA | E69: Seguimiento automático + IA
B70: Audio | C70: E/S (según modelo) | D70: E/S integrada | E70: Micrófono/altavoz integrado
B71: Protección | C71: IP66 / NEMA 4X | D71: IP66 | E71: IP66
B72: PoE | C72: 802.3at | D72: 802.3at | E72: 802.3at
... B74: Temp. Operación | C74: -30 °C a +50 °C | D74: -30 °C a +55 °C | E74: -20 °C a +50 °C
B75: Precio Ref. (USD) | C75: 5480 | D75: 3200 | E75: 180
B77: 5. Mini PTZ
B78: PTZ compacto y económico para interiores y fachadas
B79: Especificación | C79: Axis Communications AXIS P5522-E | D79: Dahua Technology DH-SD29204T-GN-W | E79: Hikvision DS-2DE2A404IW-DE3
B80: Nivel | C80: Premium | D80: Medio | E80: Medio
B81: Resolución | C81: 4 MP | D81: 4 MP | E81: 4 MP
B82: Resolución Máx. | C82: 2560 × 1440 | D82: 2560 × 1440 | E82: 2560 × 1440
B83: Sensor | C83: 1/2.8" CMOS | D83: 1/2.8" CMOS | E83: 1/2.8" CMOS
B84: Lente | C84: 10× zoom óptico (4.7–47 mm) | D84: 25× zoom óptico | E84: Zoom motorizado 2.8–8 mm
B85: Visión Nocturna | C85: IR 30 m | D85: IR 50 m | E85: IR 30 m
B86: WDR | C86: WDR | D86: WDR 120 dB | E86: WDR 120 dB
B87: Analíticas IA | C87: Autotracking básico | D87: Autotracking | E87: Autotracking básico
B88: Audio | C88: E/S (según modelo) | D88: 1 E / 1 S (según modelo) | E88: 1 E / 1 S (según modelo)
B89: Protección | C89: IP55 | D89: IP66 | E89: IP66
B90: PoE | C90: 802.3at | D90: 802.3af | E90: 802.3af
... B92: Temp. Operación | C92: -30 °C a +50 °C | D92: -30 °C a +60 °C | E92: -30 °C a +60 °C
B93: Precio Ref. (USD) | C93: 1650 | D93: 260 | E93: 210
B95: 6. Turrón (Box)
B96: Cuerpo modular con lente intercambiable; máxima flexibilidad óptica
B97: Especificación | C97: Axis Communications AXIS P1377 | D97: Hikvision DS-2CD6047FWD-A | E97: Dahua Technology DH-IPC-HF82350E
B98: Nivel | C98: Premium | D98: Medio | E98: Medio
B99: Resolución | C99: 4 MP | D99: 4 MP | E99: 4 MP
B100: Resolución Máx. | C100: 2560 × 1440 | D100: 2560 × 1440 | E100: 2560 × 1440
B101: Sensor | C101: 1/2.8" Sony Starvis | D101: 1/3" CMOS | E101: 1/1.8" CMOS
B102: Lente | C102: C/CS — lente no incluida | D102: C/CS — lente no incluida | E102: C/CS — lente no incluida
B103: Visión Nocturna | C103: Según lente instalada | D103: Según lente instalada | E103: Según lente instalada
B104: WDR | C104: Forensic WDR | D104: WDR 120 dB | E104: WDR 120 dB
B105: Analíticas IA | C105: AXIS Object Analytics | D105: Analíticas básicas | E105: IVS + analíticas
B106: Audio | C106: E/S (según modelo) | D106: 1 E / 1 S (según modelo) | E106: 1 E / 1 S (según modelo)
B107: Protección | C107: IP52 (interior) | D107: Interior | E107: Interior
B108: PoE | C108: 802.3af | D108: 802.3af | E108: 802.3af
... B110: Temp. Operación | C110: -30 °C a +50 °C | D110: -30 °C a +60 °C | E110: -30 °C a +60 °C
B111: Precio Ref. (USD) | C111: 590 | D111: 185 | E111: 190
B113: 7. Ojo de Pez (Fisheye)
B114: Lente 360° con vista panorámica desenvuelta (ePTZ)
B115: Especificación | C115: Axis Communications AXIS M3075-PLVE | D115: Hanwha Vision (Wisenet) XNF-9010RW | E115: Uniview (UNV) IPC868ER-VF18-B-M
...

Sheet Lista de Precios
B2: Lista de Precios / Cotización — Cámaras y Equipamiento
B4: Cliente:
B5: Proyecto:
B6: Fecha:
B7: Elaborado por:
B9: A. Cámaras — Base de Datos (968 modelos: 20 marcas × 14 tipos × 5 variantes)
B10: N° | C10: Marca | D10: Tipo de Cámara | E10: Modelo | F10: Precio Unit. (USD) | G10: Cantidad | H10: Descuento | I10: Subtotal (USD) | J10: Notas
B11: 1 | C11: Axis Communications | D11: Domo | E11: AXIS M3086-V | F11: =IF('Base de Datos'!AB5="","",'Base de Datos'!AB5) -> 545 | I11: =IF(OR($G11="",$G11=0),"",IFERROR(ROUND($F11*$G11*(1-IF($H11="",0,$H11)),2),""))
B12: 2 | C12: Axis Communications | D12: Domo | E12: AXIS M3206-LVE | F12: =IF('Base de Datos'!AB6="","",'Base de Datos'!AB6) -> 820 | I12: =IF(OR($G12="",$G12=0),"",IFERROR(ROUND($F12*$G12*(1-IF($H12="",0,$H12)),2),""))
B13: 3 | C13: Axis Communications | D13: Domo | E13: AXIS P3245-LVE | F13: =IF('Base de Datos'!AB7="","",'Base de Datos'!AB7) -> 1090 | I13: =IF(OR($G13="",$G13=0),"",IFERROR(ROUND($F13*$G13*(1-IF($H13="",0,$H13)),2),""))
B14: 4 | C14: Axis Communications | D14: Domo | E14: AXIS P3265-LVE | F14: =IF('Base de Datos'!AB8="","",'Base de Datos'!AB8) -> 1635 | I14: =IF(OR($G14="",$G14=0),"",IFERROR(ROUND($F14*$G14*(1-IF($H14="",0,$H14)),2),""))
B15: 5 | C15: Axis Communications | D15: Domo | E15: AXIS P3268-LVE | F15: =IF('Base de Datos'!AB9="","",'Base de Datos'!AB9) -> 2400 | I15: =IF(OR($G15="",$G15=0),"",IFERROR(ROUND($F15*$G15*(1-IF($H15="",0,$H15)),2),""))
B16: 6 | C16: Axis Communications | D16: Domo Antivandálica | E16: AXIS M3206-LVE | F16: =IF('Base de Datos'!AB10="","",'Base de Datos'!AB10) -> 345 | I16: =IF(OR($G16="",$G16=0),"",IFERROR(ROUND($F16*$G16*(1-IF($H16="",0,$H16)),2),""))
B17: 7 | C17: Axis Communications | D17: Domo Antivandálica | E17: AXIS P3245-LVE | F17: =IF('Base de Datos'!AB11="","",'Base de Datos'!AB11) -> 520 | I17: =IF(OR($G17="",$G17=0),"",IFERROR(ROUND($F17*$G17*(1-IF($H17="",0,$H17)),2),""))
B18: 8 | C18: Axis Communications | D18: Domo Antivandálica | E18: AXIS P3265-LVE | F18: =IF('Base de Datos'!AB12="","",'Base de Datos'!AB12) -> 690 | I18: =IF(OR($G18="",$G18=0),"",IFERROR(ROUND($F18*$G18*(1-IF($H18="",0,$H18)),2),""))
B19: 9 | C19: Axis Communications | D19: Domo Antivandálica | E19: AXIS Q3511-LVE | F19: =IF('Base de Datos'!AB13="","",'Base de Datos'!AB13) -> 1035 | I19: =IF(OR($G19="",$G19=0),"",IFERROR(ROUND($F19*$G19*(1-IF($H19="",0,$H19)),2),""))
B20: 10 | C20: Axis Communications | D20: Domo Antivandálica | E20: AXIS Q3536-SLVE | F20: =IF('Base de Datos'!AB14="","",'Base de Datos'!AB14) -> 1520 | I20: =IF(OR($G20="",$G20=0),"",IFERROR(ROUND($F20*$G20*(1-IF($H20="",0,$H20)),2),""))
B21: 11 | C21: Axis Communications | D21: Bala | E21: AXIS M1135 | F21: =IF('Base de Datos'!AB15="","",'Base de Datos'!AB15) -> 470 | I21: =IF(OR($G21="",$G21=0),"",IFERROR(ROUND($F21*$G21*(1-IF($H21="",0,$H21)),2),""))
B22: 12 | C22: Axis Communications | D22: Bala | E22: AXIS P1465-LE | F22: =IF('Base de Datos'!AB16="","",'Base de Datos'!AB16) -> 705 | I22: =IF(OR($G22="",$G22=0),"",IFERROR(ROUND($F22*$G22*(1-IF($H22="",0,$H22)),2),""))
... B978: 968 | C978: Tenda Security | D978: Interior WiFi | E978: CP7 | F978: =IF('Base de Datos'!AB972="","",'Base de Datos'!AB972) -> 60 | I978: =IF(OR($G978="",$G978=0),"",IFERROR(ROUND($F978*$G978*(1-IF($H978="",0,$H978)),2),""))
B979: Subtotal A — Cámaras (USD) | I979: =SUM(I11:I978) -> 0
B981: B. Equipamiento — NVR, Switch, UPS, Monitores, Rack y más (62 modelos)
B982: N° | C982: Marca | D982: Categoría | E982: Modelo | F982: Precio Unit. (USD) | G982: Cantidad | H982: Descuento | I982: Subtotal (USD) | J982: Notas
B983: 1 | C983: Axis Communications | D983: NVR / DVR | E983: AXIS S3008 Recorder | F983: =IF(Equipamiento!O5="","",Equipamiento!O5) -> 449 | I983: =IF(OR($G983="",$G983=0),"",IFERROR(ROUND($F983*$G983*(1-IF($H983="",0,$H983)),2),""))
B984: 2 | C984: Hikvision | D984: NVR / DVR | E984: DS-7608NXI-K2/8P | F984: =IF(Equipamiento!O6="","",Equipamiento!O6) -> 289 | I984: =IF(OR($G984="",$G984=0),"",IFERROR(ROUND($F984*$G984*(1-IF($H984="",0,$H984)),2),""))
B985: 3 | C985: Hikvision | D985: NVR / DVR | E985: DS-7208HUHI-K2 | F985: =IF(Equipamiento!O7="","",Equipamiento!O7) -> 139 | I985: =IF(OR($G985="",$G985=0),"",IFERROR(ROUND($F985*$G985*(1-IF($H985="",0,$H985)),2),""))
B986: 4 | C986: Dahua Technology | D986: NVR / DVR | E986: NVR5216-16P-4KS2E | F986: =IF(Equipamiento!O8="","",Equipamiento!O8) -> 519 | I986: =IF(OR($G986="",$G986=0),"",IFERROR(ROUND($F986*$G986*(1-IF($H986="",0,$H986)),2),""))
B987: 5 | C987: Uniview (UNV) | D987: NVR / DVR | E987: NVR302-16S-P16 | F987: =IF(Equipamiento!O9="","",Equipamiento!O9) -> 379 | I987: =IF(OR($G987="",$G987=0),"",IFERROR(ROUND($F987*$G987*(1-IF($H987="",0,$H987)),2),""))
B988: 6 | C988: Hanwha Vision (Wisenet) | D988: NVR / DVR | E988: HRX-810-4TB | F988: =IF(Equipamiento!O10="","",Equipamiento!O10) -> 439 | I988: =IF(OR($G988="",$G988=0),"",IFERROR(ROUND($F988*$G988*(1-IF($H988="",0,$H988)),2),""))
B989: 7 | C989: Reolink | D989: NVR / DVR | E989: RLN16-410 | F989: =IF(Equipamiento!O11="","",Equipamiento!O11) -> 269 | I989: =IF(OR($G989="",$G989=0),"",IFERROR(ROUND($F989*$G989*(1-IF($H989="",0,$H989)),2),""))
B990: 8 | C990: TP-Link VIGI | D990: NVR / DVR | E990: VIGI NVR1008H-8P | F990: =IF(Equipamiento!O12="","",Equipamiento!O12) -> 159 | I990: =IF(OR($G990="",$G990=0),"",IFERROR(ROUND($F990*$G990*(1-IF($H990="",0,$H990)),2),""))
B991: 9 | C991: HiLook (Hikvision) | D991: NVR / DVR | E991: NVR-208MH-C/8P | F991: =IF(Equipamiento!O13="","",Equipamiento!O13) -> 139 | I991: =IF(OR($G991="",$G991=0),"",IFERROR(ROUND($F991*$G991*(1-IF($H991="",0,$H991)),2),""))
B992: 10 | C992: Imou (Dahua) | D992: NVR / DVR | E992: NVR1008H-08P | F992: =IF(Equipamiento!O14="","",Equipamiento!O14) -> 119 | I992: =IF(OR($G992="",$G992=0),"",IFERROR(ROUND($F992*$G992*(1-IF($H992="",0,$H992)),2),""))
B993: 11 | C993: Seagate | D993: Almacenamiento (HDD) | E993: SkyHawk AI 8 TB (ST8000VE001) | F993: =IF(Equipamiento!O15="","",Equipamiento!O15) -> 189 | I993: =IF(OR($G993="",$G993=0),"",IFERROR(ROUND($F993*$G993*(1-IF($H993="",0,$H993)),2),""))
B994: 12 | C994: Western Digital | D994: Almacenamiento (HDD) | E994: Purple Pro 8 TB (WD82PURP) | F994: =IF(Equipamiento!O16="","",Equipamiento!O16) -> 185 | I994: =IF(OR($G994="",$G994=0),"",IFERROR(ROUND($F994*$G994*(1-IF($H994="",0,$H994)),2),""))
... B1044: 62 | C1044: Perspective Software | D1044: Software VMS | E1044: Blue Iris v5 (licencia) | F1044: =IF(Equipamiento!O66="","",Equipamiento!O66) -> 70 | I1044: =IF(OR($G1044="",$G1044=0),"",IFERROR(ROUND($F1044*$G1044*(1-IF($H1044="",0,$H1044)),2),""))
B1045: Subtotal B — Equipamiento (USD) | I1045: =SUM(I983:I1044) -> 0
B1047: TOTAL GENERAL COTIZADO (USD) | I1047: =I979+I1045 -> 0
B1049: Ítems cotizados: | D1049: =COUNTIF(G11:G978,">0")+COUNTIF(G983:G1044,">0") -> 0
B1050: Monto total con descuentos (USD): | D1050: =I1047 -> 0
B1052: Instrucciones: complete los datos del encabezado; en la sección A (cámaras) y la sección B (equipamiento) ingrese Cantidad y Descuento (0%–90%) por ítem; Subtotales y TOTAL GENERAL se calculan automáticamente. Los precios unitarios provienen de las hojas Base de Datos y Equipamiento (columna Precio Ref.), donde puede editarlos. Precios referenciales en USD.
